{
"meta":{"test_sets":[],"test_metrics":[],"learn_metrics":[{"best_value":"Min","name":"RMSE"}],"launch_mode":"Train","parameters":"","iteration_count":1000,"learn_sets":["learn"],"name":"experiment"},
"iterations":[
{"learn":[14.61268541],"iteration":0,"passed_time":0.1448345401,"remaining_time":144.6897055},
{"learn":[14.23196558],"iteration":1,"passed_time":0.145817077,"remaining_time":72.76272144},
{"learn":[13.86674177],"iteration":2,"passed_time":0.1467625049,"remaining_time":48.77407246},
{"learn":[13.49946468],"iteration":3,"passed_time":0.1475079745,"remaining_time":36.72948565},
{"learn":[13.16661202],"iteration":4,"passed_time":0.1482762959,"remaining_time":29.50698288},
{"learn":[12.85632158],"iteration":5,"passed_time":0.1491787945,"remaining_time":24.71395363},
{"learn":[12.56784336],"iteration":6,"passed_time":0.1502068173,"remaining_time":21.30790994},
{"learn":[12.31617801],"iteration":7,"passed_time":0.1510120276,"remaining_time":18.72549142},
{"learn":[12.01509946],"iteration":8,"passed_time":0.1517740128,"remaining_time":16.71200519},
{"learn":[11.71512571],"iteration":9,"passed_time":0.1525398884,"remaining_time":15.10144896},
{"learn":[11.43264457],"iteration":10,"passed_time":0.1533354403,"remaining_time":13.78625004},
{"learn":[11.17973129],"iteration":11,"passed_time":0.1540929316,"remaining_time":12.6869847},
{"learn":[10.93746433],"iteration":12,"passed_time":0.1547687685,"remaining_time":11.75052112},
{"learn":[10.69387075],"iteration":13,"passed_time":0.1555275819,"remaining_time":10.95358541},
{"learn":[10.4615922],"iteration":14,"passed_time":0.1573090837,"remaining_time":10.32996317},
{"learn":[10.2299235],"iteration":15,"passed_time":0.1582936394,"remaining_time":9.735058826},
{"learn":[10.01419731],"iteration":16,"passed_time":0.1595234997,"remaining_time":9.224211778},
{"learn":[9.795856918],"iteration":17,"passed_time":0.1602900881,"remaining_time":8.744714805},
{"learn":[9.60040151],"iteration":18,"passed_time":0.1609833273,"remaining_time":8.311823371},
{"learn":[9.418664989],"iteration":19,"passed_time":0.1616913894,"remaining_time":7.922878082},
{"learn":[9.249278645],"iteration":20,"passed_time":0.1625498512,"remaining_time":7.577919254},
{"learn":[9.090113396],"iteration":21,"passed_time":0.1633054406,"remaining_time":7.259669134},
{"learn":[8.909548708],"iteration":22,"passed_time":0.1639872607,"remaining_time":6.965893639},
{"learn":[8.740140208],"iteration":23,"passed_time":0.1646704523,"remaining_time":6.696598395},
{"learn":[8.59377682],"iteration":24,"passed_time":0.1654465201,"remaining_time":6.452414283},
{"learn":[8.453885414],"iteration":25,"passed_time":0.166207485,"remaining_time":6.226388092},
{"learn":[8.317732234],"iteration":26,"passed_time":0.1669494743,"remaining_time":6.016364389},
{"learn":[8.180896085],"iteration":27,"passed_time":0.1676504902,"remaining_time":5.819867016},
{"learn":[8.053220863],"iteration":28,"passed_time":0.1685111279,"remaining_time":5.642217419},
{"learn":[7.924234474],"iteration":29,"passed_time":0.1702819249,"remaining_time":5.50578224},
{"learn":[7.818879511],"iteration":30,"passed_time":0.1712575963,"remaining_time":5.353180994},
{"learn":[7.719346395],"iteration":31,"passed_time":0.1725953523,"remaining_time":5.221009407},
{"learn":[7.624163594],"iteration":32,"passed_time":0.1733617129,"remaining_time":5.080023526},
{"learn":[7.524952543],"iteration":33,"passed_time":0.1741164896,"remaining_time":4.946956734},
{"learn":[7.424464745],"iteration":34,"passed_time":0.1747905859,"remaining_time":4.819226155},
{"learn":[7.327482321],"iteration":35,"passed_time":0.1755217889,"remaining_time":4.700083459},
{"learn":[7.238666841],"iteration":36,"passed_time":0.1762271112,"remaining_time":4.586667787},
{"learn":[7.158842395],"iteration":37,"passed_time":0.1769829478,"remaining_time":4.480463046},
{"learn":[7.074348246],"iteration":38,"passed_time":0.1777018433,"remaining_time":4.378755676},
{"learn":[6.992269093],"iteration":39,"passed_time":0.1783921073,"remaining_time":4.281410575},
{"learn":[6.925219745],"iteration":40,"passed_time":0.1791273058,"remaining_time":4.189831372},
{"learn":[6.86013671],"iteration":41,"passed_time":0.1799329589,"remaining_time":4.104185111},
{"learn":[6.786739622],"iteration":42,"passed_time":0.1806285934,"remaining_time":4.02003637},
{"learn":[6.73057926],"iteration":43,"passed_time":0.1813511659,"remaining_time":3.94026624},
{"learn":[6.666356486],"iteration":44,"passed_time":0.1824530454,"remaining_time":3.872059075},
{"learn":[6.606182832],"iteration":45,"passed_time":0.1839864449,"remaining_time":3.815718878},
{"learn":[6.547854615],"iteration":46,"passed_time":0.1848288558,"remaining_time":3.747699991},
{"learn":[6.49240675],"iteration":47,"passed_time":0.1858537471,"remaining_time":3.686099317},
{"learn":[6.431317261],"iteration":48,"passed_time":0.1868165419,"remaining_time":3.625765946},
{"learn":[6.377586395],"iteration":49,"passed_time":0.1878130253,"remaining_time":3.56844748},
{"learn":[6.327558015],"iteration":50,"passed_time":0.1885584865,"remaining_time":3.508666738},
{"learn":[6.282040317],"iteration":51,"passed_time":0.1893641615,"remaining_time":3.452254328},
{"learn":[6.237655841],"iteration":52,"passed_time":0.1901124037,"remaining_time":3.396914081},
{"learn":[6.192792003],"iteration":53,"passed_time":0.1907932203,"remaining_time":3.342414562},
{"learn":[6.150579347],"iteration":54,"passed_time":0.191500605,"remaining_time":3.290328577},
{"learn":[6.115693845],"iteration":55,"passed_time":0.1922639282,"remaining_time":3.241020504},
{"learn":[6.078780782],"iteration":56,"passed_time":0.1930542684,"remaining_time":3.193862722},
{"learn":[6.045146957],"iteration":57,"passed_time":0.1937703703,"remaining_time":3.147098083},
{"learn":[6.008080327],"iteration":58,"passed_time":0.1946272916,"remaining_time":3.104140362},
{"learn":[5.977575734],"iteration":59,"passed_time":0.1957333994,"remaining_time":3.066489924},
{"learn":[5.948036502],"iteration":60,"passed_time":0.1969318673,"remaining_time":3.0314594},
{"learn":[5.914888282],"iteration":61,"passed_time":0.1982377771,"remaining_time":2.999145725},
{"learn":[5.884957796],"iteration":62,"passed_time":0.1995115684,"remaining_time":2.967338724},
{"learn":[5.849539885],"iteration":63,"passed_time":0.200550417,"remaining_time":2.933049848},
{"learn":[5.821387627],"iteration":64,"passed_time":0.2014852065,"remaining_time":2.898287201},
{"learn":[5.797012279],"iteration":65,"passed_time":0.2023993201,"remaining_time":2.864257045},
{"learn":[5.768685095],"iteration":66,"passed_time":0.2033059286,"remaining_time":2.831110916},
{"learn":[5.755484587],"iteration":67,"passed_time":0.2037881333,"remaining_time":2.79309618},
{"learn":[5.731887055],"iteration":68,"passed_time":0.2047367195,"remaining_time":2.762462114},
{"learn":[5.707148487],"iteration":69,"passed_time":0.2056573399,"remaining_time":2.732304659},
{"learn":[5.685365039],"iteration":70,"passed_time":0.2065878482,"remaining_time":2.703100155},
{"learn":[5.663541834],"iteration":71,"passed_time":0.207433594,"remaining_time":2.673588545},
{"learn":[5.638108797],"iteration":72,"passed_time":0.2083807104,"remaining_time":2.646149568},
{"learn":[5.619204893],"iteration":73,"passed_time":0.2104490491,"remaining_time":2.63345702},
{"learn":[5.598472793],"iteration":74,"passed_time":0.2113962268,"remaining_time":2.607220131},
{"learn":[5.577007075],"iteration":75,"passed_time":0.2123870304,"remaining_time":2.582179159},
{"learn":[5.562637084],"iteration":76,"passed_time":0.2134132428,"remaining_time":2.558187314},
{"learn":[5.54729991],"iteration":77,"passed_time":0.2142212215,"remaining_time":2.532204695},
{"learn":[5.530737623],"iteration":78,"passed_time":0.2150335092,"remaining_time":2.506909645},
{"learn":[5.513704873],"iteration":79,"passed_time":0.2158888462,"remaining_time":2.482721731},
{"learn":[5.501575529],"iteration":80,"passed_time":0.2167293695,"remaining_time":2.458941859},
{"learn":[5.484080734],"iteration":81,"passed_time":0.217466633,"remaining_time":2.434565476},
{"learn":[5.472178894],"iteration":82,"passed_time":0.2183001368,"remaining_time":2.411821994},
{"learn":[5.458923342],"iteration":83,"passed_time":0.2191249606,"remaining_time":2.389505523},
{"learn":[5.451382371],"iteration":84,"passed_time":0.2197219241,"remaining_time":2.365241889},
{"learn":[5.441410748],"iteration":85,"passed_time":0.2205359246,"remaining_time":2.343835291},
{"learn":[5.434047468],"iteration":86,"passed_time":0.2210769168,"remaining_time":2.320037069},
{"learn":[5.422107497],"iteration":87,"passed_time":0.2218981754,"remaining_time":2.299671999},
{"learn":[5.40731265],"iteration":88,"passed_time":0.2249733358,"remaining_time":2.302816954},
{"learn":[5.396360181],"iteration":89,"passed_time":0.2262360744,"remaining_time":2.287498085},
{"learn":[5.383793239],"iteration":90,"passed_time":0.227258973,"remaining_time":2.270092378},
{"learn":[5.369605034],"iteration":91,"passed_time":0.2280000327,"remaining_time":2.250261193},
{"learn":[5.357467333],"iteration":92,"passed_time":0.2286779691,"remaining_time":2.230224924},
{"learn":[5.341109968],"iteration":93,"passed_time":0.2295854045,"remaining_time":2.212812516},
{"learn":[5.330529276],"iteration":94,"passed_time":0.2303770332,"remaining_time":2.194644369},
{"learn":[5.319862075],"iteration":95,"passed_time":0.2310862156,"remaining_time":2.176061864},
{"learn":[5.313052243],"iteration":96,"passed_time":0.2318601377,"remaining_time":2.15845056},
{"learn":[5.299677207],"iteration":97,"passed_time":0.23318239,"remaining_time":2.146229753},
{"learn":[5.287546698],"iteration":98,"passed_time":0.2341403313,"remaining_time":2.13091352},
{"learn":[5.279803754],"iteration":99,"passed_time":0.235035492,"remaining_time":2.115319428},
{"learn":[5.272254612],"iteration":100,"passed_time":0.2359809233,"remaining_time":2.100463861},
{"learn":[5.268813888],"iteration":101,"passed_time":0.2372278488,"remaining_time":2.088535375},
{"learn":[5.258113767],"iteration":102,"passed_time":0.2382175338,"remaining_time":2.074574056},
{"learn":[5.251018576],"iteration":103,"passed_time":0.2396707571,"remaining_time":2.064855753},
{"learn":[5.24171237],"iteration":104,"passed_time":0.241789131,"remaining_time":2.060964498},
{"learn":[5.233984943],"iteration":105,"passed_time":0.2433382443,"remaining_time":2.05230557},
{"learn":[5.226240449],"iteration":106,"passed_time":0.2441805569,"remaining_time":2.037880722},
{"learn":[5.220541644],"iteration":107,"passed_time":0.2449411016,"remaining_time":2.023032061},
{"learn":[5.211712096],"iteration":108,"passed_time":0.2458441331,"remaining_time":2.009606629},
{"learn":[5.203388597],"iteration":109,"passed_time":0.2469512562,"remaining_time":1.998060164},
{"learn":[5.196026544],"iteration":110,"passed_time":0.2477559975,"remaining_time":1.984280016},
{"learn":[5.188716772],"iteration":111,"passed_time":0.2485497903,"remaining_time":1.970644766},
{"learn":[5.182163132],"iteration":112,"passed_time":0.2492597627,"remaining_time":1.956578846},
{"learn":[5.17764747],"iteration":113,"passed_time":0.2499679014,"remaining_time":1.942732988},
{"learn":[5.170548056],"iteration":114,"passed_time":0.2506865414,"remaining_time":1.929196427},
{"learn":[5.165901827],"iteration":115,"passed_time":0.2535402382,"remaining_time":1.932151471},
{"learn":[5.160333668],"iteration":116,"passed_time":0.2550402038,"remaining_time":1.924790598},
{"learn":[5.148953243],"iteration":117,"passed_time":0.25591533,"remaining_time":1.912858653},
{"learn":[5.144729126],"iteration":118,"passed_time":0.2564986413,"remaining_time":1.898952126},
{"learn":[5.139939946],"iteration":119,"passed_time":0.2571558614,"remaining_time":1.88580965},
{"learn":[5.132898872],"iteration":120,"passed_time":0.257873951,"remaining_time":1.873315726},
{"learn":[5.129073077],"iteration":121,"passed_time":0.2586988453,"remaining_time":1.861783493},
{"learn":[5.127123916],"iteration":122,"passed_time":0.2591258746,"remaining_time":1.847588553},
{"learn":[5.121282057],"iteration":123,"passed_time":0.2599000648,"remaining_time":1.8360682},
{"learn":[5.114489821],"iteration":124,"passed_time":0.2605879403,"remaining_time":1.824115582},
{"learn":[5.107777291],"iteration":125,"passed_time":0.2612582235,"remaining_time":1.812219741},
{"learn":[5.103518754],"iteration":126,"passed_time":0.262020139,"remaining_time":1.801130562},
{"learn":[5.101133351],"iteration":127,"passed_time":0.2625055802,"remaining_time":1.788319265},
{"learn":[5.096462705],"iteration":128,"passed_time":0.2632426823,"remaining_time":1.777398266},
{"learn":[5.08562082],"iteration":129,"passed_time":0.263956183,"remaining_time":1.766475994},
{"learn":[5.080483682],"iteration":130,"passed_time":0.2646429399,"remaining_time":1.755532174},
{"learn":[5.07437499],"iteration":131,"passed_time":0.2657049007,"remaining_time":1.747211014},
{"learn":[5.070683732],"iteration":132,"passed_time":0.2672656323,"remaining_time":1.7422504},
{"learn":[5.06432037],"iteration":133,"passed_time":0.2683033001,"remaining_time":1.733960133},
{"learn":[5.057436484],"iteration":134,"passed_time":0.2692756416,"remaining_time":1.72535874},
{"learn":[5.053254656],"iteration":135,"passed_time":0.2700738433,"remaining_time":1.71576324},
{"learn":[5.04801663],"iteration":136,"passed_time":0.2707356582,"remaining_time":1.705437029},
{"learn":[5.045680836],"iteration":137,"passed_time":0.2713313988,"remaining_time":1.694838158},
{"learn":[5.041857933],"iteration":138,"passed_time":0.2721718129,"remaining_time":1.685898783},
{"learn":[5.035264888],"iteration":139,"passed_time":0.2728909479,"remaining_time":1.676330109},
{"learn":[5.028771948],"iteration":140,"passed_time":0.2735975334,"remaining_time":1.666810505},
{"learn":[5.024912247],"iteration":141,"passed_time":0.2743211447,"remaining_time":1.657517902},
{"learn":[5.02239068],"iteration":142,"passed_time":0.2749844371,"remaining_time":1.647983654},
{"learn":[5.017110572],"iteration":143,"passed_time":0.2757431042,"remaining_time":1.639139564},
{"learn":[5.010707886],"iteration":144,"passed_time":0.2765214807,"remaining_time":1.630523214},
{"learn":[5.004389868],"iteration":145,"passed_time":0.2772038873,"remaining_time":1.621452875},
{"learn":[4.997628683],"iteration":146,"passed_time":0.277937979,"remaining_time":1.612796572},
{"learn":[4.991497851],"iteration":147,"passed_time":0.2786564265,"remaining_time":1.604157266},
{"learn":[4.988345253],"iteration":148,"passed_time":0.2793703172,"remaining_time":1.595598254},
{"learn":[4.98460423],"iteration":149,"passed_time":0.2806327599,"remaining_time":1.590252306},
{"learn":[4.982441783],"iteration":150,"passed_time":0.2817096471,"remaining_time":1.583917155},
{"learn":[4.977461771],"iteration":151,"passed_time":0.2826654486,"remaining_time":1.576975661},
{"learn":[4.973601586],"iteration":152,"passed_time":0.2836843685,"remaining_time":1.570461831},
{"learn":[4.968328804],"iteration":153,"passed_time":0.2844701753,"remaining_time":1.562738755},
{"learn":[4.9640736],"iteration":154,"passed_time":0.2853162094,"remaining_time":1.555433529},
{"learn":[4.960865882],"iteration":155,"passed_time":0.2860155133,"remaining_time":1.547417264},
{"learn":[4.957014156],"iteration":156,"passed_time":0.2867415114,"remaining_time":1.539637542},
{"learn":[4.952244852],"iteration":157,"passed_time":0.2874530379,"remaining_time":1.531869987},
{"learn":[4.949695675],"iteration":158,"passed_time":0.2881691238,"remaining_time":1.524215303},
{"learn":[4.946584698],"iteration":159,"passed_time":0.2889173089,"remaining_time":1.516815872},
{"learn":[4.940192834],"iteration":160,"passed_time":0.2896933817,"remaining_time":1.509644393},
{"learn":[4.936727994],"iteration":161,"passed_time":0.2904759385,"remaining_time":1.50258541},
{"learn":[4.932342063],"iteration":162,"passed_time":0.2911800733,"remaining_time":1.495200744},
{"learn":[4.925830838],"iteration":163,"passed_time":0.2918567473,"remaining_time":1.487757565},
{"learn":[4.922571773],"iteration":164,"passed_time":0.2926058921,"remaining_time":1.480763151},
{"learn":[4.918395814],"iteration":165,"passed_time":0.293350565,"remaining_time":1.473821513},
{"learn":[4.911142452],"iteration":166,"passed_time":0.2939989411,"remaining_time":1.46647376},
{"learn":[4.908276131],"iteration":167,"passed_time":0.2951971838,"remaining_time":1.46192891},
{"learn":[4.904584645],"iteration":168,"passed_time":0.2964669788,"remaining_time":1.457775499},
{"learn":[4.89795517],"iteration":169,"passed_time":0.297614487,"remaining_time":1.453058966},
{"learn":[4.895556491],"iteration":170,"passed_time":0.2984879558,"remaining_time":1.447055646},
{"learn":[4.890591233],"iteration":171,"passed_time":0.2992542778,"remaining_time":1.440596174},
{"learn":[4.884629277],"iteration":172,"passed_time":0.3000610941,"remaining_time":1.434396097},
{"learn":[4.880550786],"iteration":173,"passed_time":0.3008331412,"remaining_time":1.428092957},
{"learn":[4.876384842],"iteration":174,"passed_time":0.3015426379,"remaining_time":1.42155815},
{"learn":[4.872638238],"iteration":175,"passed_time":0.3023029801,"remaining_time":1.415327589},
{"learn":[4.869137118],"iteration":176,"passed_time":0.3032167609,"remaining_time":1.409872284},
{"learn":[4.863587157],"iteration":177,"passed_time":0.3039768594,"remaining_time":1.403758306},
{"learn":[4.858028614],"iteration":178,"passed_time":0.3046629548,"remaining_time":1.397364725},
{"learn":[4.853838176],"iteration":179,"passed_time":0.3053502032,"remaining_time":1.391039815},
{"learn":[4.853462329],"iteration":180,"passed_time":0.3057241508,"remaining_time":1.383359555},
{"learn":[4.851573196],"iteration":181,"passed_time":0.3063674414,"remaining_time":1.376970149},
{"learn":[4.848442087],"iteration":182,"passed_time":0.3072242416,"remaining_time":1.371596751},
{"learn":[4.845547104],"iteration":183,"passed_time":0.307976876,"remaining_time":1.365810494},
{"learn":[4.839868817],"iteration":184,"passed_time":0.30996421,"remaining_time":1.365518006},
{"learn":[4.836336958],"iteration":185,"passed_time":0.3116674184,"remaining_time":1.363963863},
{"learn":[4.831124789],"iteration":186,"passed_time":0.3125455861,"remaining_time":1.358821185},
{"learn":[4.827407333],"iteration":187,"passed_time":0.3134575701,"remaining_time":1.35386993},
{"learn":[4.824088918],"iteration":188,"passed_time":0.3143532511,"remaining_time":1.348891464},
{"learn":[4.820934539],"iteration":189,"passed_time":0.315238113,"remaining_time":1.34390985},
{"learn":[4.816975227],"iteration":190,"passed_time":0.3159968062,"remaining_time":1.338436734},
{"learn":[4.812340486],"iteration":191,"passed_time":0.3166696502,"remaining_time":1.332651445},
{"learn":[4.806402747],"iteration":192,"passed_time":0.3173569592,"remaining_time":1.326979617},
{"learn":[4.801521788],"iteration":193,"passed_time":0.3183096166,"remaining_time":1.322461603},
{"learn":[4.797601172],"iteration":194,"passed_time":0.3194465739,"remaining_time":1.318740985},
{"learn":[4.792694629],"iteration":195,"passed_time":0.3203453477,"remaining_time":1.314069692},
{"learn":[4.789794613],"iteration":196,"passed_time":0.3211586288,"remaining_time":1.309088218},
{"learn":[4.785367055],"iteration":197,"passed_time":0.3222019948,"remaining_time":1.305080807},
{"learn":[4.780376856],"iteration":198,"passed_time":0.3252638358,"remaining_time":1.309227801},
{"learn":[4.776691261],"iteration":199,"passed_time":0.3265182111,"remaining_time":1.306072844},
{"learn":[4.773470753],"iteration":200,"passed_time":0.3276827855,"remaining_time":1.302579829},
{"learn":[4.77207327],"iteration":201,"passed_time":0.3287936099,"remaining_time":1.298897528},
{"learn":[4.767347177],"iteration":202,"passed_time":0.3296467929,"remaining_time":1.294229034},
{"learn":[4.763983068],"iteration":203,"passed_time":0.3303504452,"remaining_time":1.289014482},
{"learn":[4.761588849],"iteration":204,"passed_time":0.3310245625,"remaining_time":1.283729401},
{"learn":[4.758558086],"iteration":205,"passed_time":0.3316699484,"remaining_time":1.278378345},
{"learn":[4.753678804],"iteration":206,"passed_time":0.3327244503,"remaining_time":1.274640044},
{"learn":[4.746510889],"iteration":207,"passed_time":0.3337401412,"remaining_time":1.270779768},
{"learn":[4.744840601],"iteration":208,"passed_time":0.3346900663,"remaining_time":1.266697811},
{"learn":[4.741702222],"iteration":209,"passed_time":0.3353913838,"remaining_time":1.261710444},
{"learn":[4.739352853],"iteration":210,"passed_time":0.3361829385,"remaining_time":1.25710113},
{"learn":[4.735539287],"iteration":211,"passed_time":0.3371947011,"remaining_time":1.253346342},
{"learn":[4.730726751],"iteration":212,"passed_time":0.3393164646,"remaining_time":1.25371858},
{"learn":[4.726416092],"iteration":213,"passed_time":0.340597345,"remaining_time":1.250979034},
{"learn":[4.721293082],"iteration":214,"passed_time":0.3415080414,"remaining_time":1.246901454},
{"learn":[4.718443695],"iteration":215,"passed_time":0.3424276197,"remaining_time":1.242885434},
{"learn":[4.711627962],"iteration":216,"passed_time":0.3432568449,"remaining_time":1.238571933},
{"learn":[4.709790764],"iteration":217,"passed_time":0.3439840532,"remaining_time":1.233924448},
{"learn":[4.706913073],"iteration":218,"passed_time":0.3446659447,"remaining_time":1.229151154},
{"learn":[4.703846389],"iteration":219,"passed_time":0.3453946037,"remaining_time":1.224580868},
{"learn":[4.701001135],"iteration":220,"passed_time":0.3461357576,"remaining_time":1.22008939},
{"learn":[4.700380864],"iteration":221,"passed_time":0.3467765815,"remaining_time":1.215280092},
{"learn":[4.695837486],"iteration":222,"passed_time":0.3475419016,"remaining_time":1.210941962},
{"learn":[4.691242996],"iteration":223,"passed_time":0.3482236948,"remaining_time":1.206346371},
{"learn":[4.690284609],"iteration":224,"passed_time":0.3490426942,"remaining_time":1.202258169},
{"learn":[4.68827119],"iteration":225,"passed_time":0.3498512562,"remaining_time":1.198163152},
{"learn":[4.686922425],"iteration":226,"passed_time":0.3505102102,"remaining_time":1.193587632},
{"learn":[4.686085874],"iteration":227,"passed_time":0.3526054332,"remaining_time":1.193909625},
{"learn":[4.683230741],"iteration":228,"passed_time":0.3536649021,"remaining_time":1.190723317},
{"learn":[4.6773487],"iteration":229,"passed_time":0.3547561206,"remaining_time":1.187661795},
{"learn":[4.671462906],"iteration":230,"passed_time":0.3556185165,"remaining_time":1.183855581},
{"learn":[4.664799601],"iteration":231,"passed_time":0.3563570751,"remaining_time":1.1796648},
{"learn":[4.660979386],"iteration":232,"passed_time":0.3570865292,"remaining_time":1.175473682},
{"learn":[4.656281279],"iteration":233,"passed_time":0.3578712812,"remaining_time":1.171493169},
{"learn":[4.651997094],"iteration":234,"passed_time":0.3585775995,"remaining_time":1.167284526},
{"learn":[4.650151977],"iteration":235,"passed_time":0.3592781716,"remaining_time":1.163086962},
{"learn":[4.648478046],"iteration":236,"passed_time":0.3599503265,"remaining_time":1.158827422},
{"learn":[4.646364602],"iteration":237,"passed_time":0.3606379364,"remaining_time":1.154647511},
{"learn":[4.642635873],"iteration":238,"passed_time":0.3613645001,"remaining_time":1.150620856},
{"learn":[4.640860821],"iteration":239,"passed_time":0.3620254569,"remaining_time":1.146413947},
{"learn":[4.639446822],"iteration":240,"passed_time":0.3627551034,"remaining_time":1.142452795},
{"learn":[4.637120072],"iteration":241,"passed_time":0.3634794475,"remaining_time":1.138501741},
{"learn":[4.633769267],"iteration":242,"passed_time":0.3641733608,"remaining_time":1.134482445},
{"learn":[4.630491517],"iteration":243,"passed_time":0.3648616867,"remaining_time":1.130473095},
{"learn":[4.627813333],"iteration":244,"passed_time":0.3665441259,"remaining_time":1.129554347},
{"learn":[4.622496304],"iteration":245,"passed_time":0.3674439318,"remaining_time":1.126230588},
{"learn":[4.618979301],"iteration":246,"passed_time":0.3686590053,"remaining_time":1.123887575},
{"learn":[4.616563458],"iteration":247,"passed_time":0.369545733,"remaining_time":1.120558029},
{"learn":[4.614759385],"iteration":248,"passed_time":0.3705478372,"remaining_time":1.117596087},
{"learn":[4.61251363],"iteration":249,"passed_time":0.3713120748,"remaining_time":1.113936225},
{"learn":[4.608796693],"iteration":250,"passed_time":0.3720389319,"remaining_time":1.110187888},
{"learn":[4.60847774],"iteration":251,"passed_time":0.3727415732,"remaining_time":1.106391654},
{"learn":[4.605195659],"iteration":252,"passed_time":0.373414424,"remaining_time":1.102531916},
{"learn":[4.60103766],"iteration":253,"passed_time":0.374105004,"remaining_time":1.098749342},
{"learn":[4.599325598],"iteration":254,"passed_time":0.3748050273,"remaining_time":1.095018609},
{"learn":[4.597012808],"iteration":255,"passed_time":0.3755166588,"remaining_time":1.09134529},
{"learn":[4.594161533],"iteration":256,"passed_time":0.3762133976,"remaining_time":1.087651963},
{"learn":[4.592197259],"iteration":257,"passed_time":0.3769251678,"remaining_time":1.084025095},
{"learn":[4.58952828],"iteration":258,"passed_time":0.3776167102,"remaining_time":1.080362866},
{"learn":[4.585816572],"iteration":259,"passed_time":0.3782833517,"remaining_time":1.076652616},
{"learn":[4.582934052],"iteration":260,"passed_time":0.3790626569,"remaining_time":1.073284687},
{"learn":[4.582234842],"iteration":261,"passed_time":0.38064139,"remaining_time":1.072188343},
{"learn":[4.57571562],"iteration":262,"passed_time":0.381749467,"remaining_time":1.069769419},
{"learn":[4.571197349],"iteration":263,"passed_time":0.3826104048,"remaining_time":1.066671431},
{"learn":[4.56723703],"iteration":264,"passed_time":0.3832917205,"remaining_time":1.063092131},
{"learn":[4.560335567],"iteration":265,"passed_time":0.3840875077,"remaining_time":1.059850491},
{"learn":[4.554709345],"iteration":266,"passed_time":0.3847973726,"remaining_time":1.056391289},
{"learn":[4.552806306],"iteration":267,"passed_time":0.3855387122,"remaining_time":1.053038572},
{"learn":[4.550766241],"iteration":268,"passed_time":0.3862281913,"remaining_time":1.049564341},
{"learn":[4.549216045],"iteration":269,"passed_time":0.3869716867,"remaining_time":1.046256782},
{"learn":[4.547687452],"iteration":270,"passed_time":0.3877394643,"remaining_time":1.043033467},
{"learn":[4.545642435],"iteration":271,"passed_time":0.3884174619,"remaining_time":1.039587913},
{"learn":[4.543930359],"iteration":272,"passed_time":0.3892221074,"remaining_time":1.036499898},
{"learn":[4.541029943],"iteration":273,"passed_time":0.3899579884,"remaining_time":1.033246349},
{"learn":[4.537781449],"iteration":274,"passed_time":0.3906040877,"remaining_time":1.029774413},
{"learn":[4.53066128],"iteration":275,"passed_time":0.3913278637,"remaining_time":1.026526715},
{"learn":[4.526763956],"iteration":276,"passed_time":0.3920377076,"remaining_time":1.023260876},
{"learn":[4.522036004],"iteration":277,"passed_time":0.3928073107,"remaining_time":1.020168627},
{"learn":[4.515307629],"iteration":278,"passed_time":0.3935349804,"remaining_time":1.016984663},
{"learn":[4.51109143],"iteration":279,"passed_time":0.3952275428,"remaining_time":1.016299396},
{"learn":[4.508233494],"iteration":280,"passed_time":0.3966341936,"remaining_time":1.014875392},
{"learn":[4.502555629],"iteration":281,"passed_time":0.3975569883,"remaining_time":1.012219566},
{"learn":[4.500081355],"iteration":282,"passed_time":0.3983940825,"remaining_time":1.009358859},
{"learn":[4.495281743],"iteration":283,"passed_time":0.3991223952,"remaining_time":1.006238151},
{"learn":[4.492138869],"iteration":284,"passed_time":0.3998729008,"remaining_time":1.003189909},
{"learn":[4.491708261],"iteration":285,"passed_time":0.4006025826,"remaining_time":1.000105748},
{"learn":[4.489398865],"iteration":286,"passed_time":0.4013101741,"remaining_time":0.9969831155},
{"learn":[4.485796373],"iteration":287,"passed_time":0.4021166694,"remaining_time":0.994121766},
{"learn":[4.479542205],"iteration":288,"passed_time":0.4029147056,"remaining_time":0.9912538259},
{"learn":[4.475986993],"iteration":289,"passed_time":0.4036833354,"remaining_time":0.9883281659},
{"learn":[4.468661855],"iteration":290,"passed_time":0.4044967223,"remaining_time":0.9855263785},
{"learn":[4.463785664],"iteration":291,"passed_time":0.4052210765,"remaining_time":0.9825223363},
{"learn":[4.460445831],"iteration":292,"passed_time":0.4059523922,"remaining_time":0.9795506528},
{"learn":[4.45692492],"iteration":293,"passed_time":0.4066881059,"remaining_time":0.9766047713},
{"learn":[4.454031688],"iteration":294,"passed_time":0.4074245087,"remaining_time":0.9736755209},
{"learn":[4.451672391],"iteration":295,"passed_time":0.40817136,"remaining_time":0.9707859374},
{"learn":[4.45031553],"iteration":296,"passed_time":0.4098211033,"remaining_time":0.9700479315},
{"learn":[4.446782666],"iteration":297,"passed_time":0.4108680614,"remaining_time":0.9678838225},
{"learn":[4.444369689],"iteration":298,"passed_time":0.411858728,"remaining_time":0.9655952118},
{"learn":[4.44411683],"iteration":299,"passed_time":0.4126878952,"remaining_time":0.9629384221},
{"learn":[4.440876943],"iteration":300,"passed_time":0.4135565205,"remaining_time":0.960385408},
{"learn":[4.439336453],"iteration":301,"passed_time":0.4142494899,"remaining_time":0.9574375627},
{"learn":[4.436666901],"iteration":302,"passed_time":0.4149847262,"remaining_time":0.954601829},
{"learn":[4.433043336],"iteration":303,"passed_time":0.4156783293,"remaining_time":0.9516845961},
{"learn":[4.431419305],"iteration":304,"passed_time":0.4165075848,"remaining_time":0.9490910538},
{"learn":[4.428859646],"iteration":305,"passed_time":0.4172715618,"remaining_time":0.9463609932},
{"learn":[4.424552441],"iteration":306,"passed_time":0.4179957269,"remaining_time":0.9435538722},
{"learn":[4.422706391],"iteration":307,"passed_time":0.4187066374,"remaining_time":0.940730497},
{"learn":[4.421427994],"iteration":308,"passed_time":0.4194807805,"remaining_time":0.9380621985},
{"learn":[4.418733158],"iteration":309,"passed_time":0.420216427,"remaining_time":0.9353204342},
{"learn":[4.415656941],"iteration":310,"passed_time":0.4209720794,"remaining_time":0.932635893},
{"learn":[4.410747417],"iteration":311,"passed_time":0.4216671457,"remaining_time":0.9298301163},
{"learn":[4.408126521],"iteration":312,"passed_time":0.4224021005,"remaining_time":0.9271253772},
{"learn":[4.407843853],"iteration":313,"passed_time":0.4241502635,"remaining_time":0.926646754},
{"learn":[4.405219398],"iteration":314,"passed_time":0.4254069366,"remaining_time":0.9250912748},
{"learn":[4.402708465],"iteration":315,"passed_time":0.4261541518,"remaining_time":0.9224349361},
{"learn":[4.40104971],"iteration":316,"passed_time":0.4269971384,"remaining_time":0.9199969891},
{"learn":[4.400830038],"iteration":317,"passed_time":0.4277501611,"remaining_time":0.9173761317},
{"learn":[4.39784288],"iteration":318,"passed_time":0.4284782881,"remaining_time":0.9147138376},
{"learn":[4.393741845],"iteration":319,"passed_time":0.429173172,"remaining_time":0.9119929906},
{"learn":[4.393425936],"iteration":320,"passed_time":0.4298758411,"remaining_time":0.9093012339},
{"learn":[4.390505974],"iteration":321,"passed_time":0.4306168983,"remaining_time":0.9067026617},
{"learn":[4.390305136],"iteration":322,"passed_time":0.4312727292,"remaining_time":0.9039369588},
{"learn":[4.38568203],"iteration":323,"passed_time":0.4319978113,"remaining_time":0.9013287667},
{"learn":[4.383057135],"iteration":324,"passed_time":0.4327680362,"remaining_time":0.8988259214},
{"learn":[4.380662684],"iteration":325,"passed_time":0.4334636934,"remaining_time":0.8961795379},
{"learn":[4.37805727],"iteration":326,"passed_time":0.4341542625,"remaining_time":0.8935346136},
{"learn":[4.373708319],"iteration":327,"passed_time":0.4348591452,"remaining_time":0.8909309317},
{"learn":[4.36887921],"iteration":328,"passed_time":0.4356246023,"remaining_time":0.8884623348},
{"learn":[4.367895929],"iteration":329,"passed_time":0.436346921,"remaining_time":0.8859164759},
{"learn":[4.362140573],"iteration":330,"passed_time":0.4370463576,"remaining_time":0.8833353875},
{"learn":[4.361931924],"iteration":331,"passed_time":0.4385578491,"remaining_time":0.8823995278},
{"learn":[4.359656377],"iteration":332,"passed_time":0.4400143182,"remaining_time":0.8813500008},
{"learn":[4.354281355],"iteration":333,"passed_time":0.4409027991,"remaining_time":0.8791654617},
{"learn":[4.348589447],"iteration":334,"passed_time":0.4416880899,"remaining_time":0.8767838203},
{"learn":[4.346355698],"iteration":335,"passed_time":0.4425096074,"remaining_time":0.8744832717},
{"learn":[4.343894047],"iteration":336,"passed_time":0.4433025151,"remaining_time":0.8721352152},
{"learn":[4.341561356],"iteration":337,"passed_time":0.4440451457,"remaining_time":0.8696978889},
{"learn":[4.338869061],"iteration":338,"passed_time":0.4448019756,"remaining_time":0.8672982475},
{"learn":[4.333720063],"iteration":339,"passed_time":0.4454825543,"remaining_time":0.8647602525},
{"learn":[4.330892223],"iteration":340,"passed_time":0.4463032473,"remaining_time":0.8625039295},
{"learn":[4.328311474],"iteration":341,"passed_time":0.4470059197,"remaining_time":0.8600289331},
{"learn":[4.324580133],"iteration":342,"passed_time":0.447682318,"remaining_time":0.8575139443},
{"learn":[4.323354432],"iteration":343,"passed_time":0.4483516834,"remaining_time":0.8549962335},
{"learn":[4.323159553],"iteration":344,"passed_time":0.4490185872,"remaining_time":0.8524845642},
{"learn":[4.318639682],"iteration":345,"passed_time":0.449824532,"remaining_time":0.8502463698},
{"learn":[4.312712208],"iteration":346,"passed_time":0.4505326631,"remaining_time":0.8478323602},
{"learn":[4.311461062],"iteration":347,"passed_time":0.4512587806,"remaining_time":0.8454618533},
{"learn":[4.311178356],"iteration":348,"passed_time":0.4532525238,"remaining_time":0.8454653094},
{"learn":[4.311102505],"iteration":349,"passed_time":0.4544833666,"remaining_time":0.8440405379},
{"learn":[4.310232308],"iteration":350,"passed_time":0.4555561599,"remaining_time":0.8423246376},
{"learn":[4.305128197],"iteration":351,"passed_time":0.4568220443,"remaining_time":0.8409678543},
{"learn":[4.304595496],"iteration":352,"passed_time":0.4578588489,"remaining_time":0.8391917146},
{"learn":[4.3004992],"iteration":353,"passed_time":0.45878565,"remaining_time":0.8372190109},
{"learn":[4.297581524],"iteration":354,"passed_time":0.4598798226,"remaining_time":0.8355562974},
{"learn":[4.297355825],"iteration":355,"passed_time":0.4608847827,"remaining_time":0.8337353934},
{"learn":[4.295758715],"iteration":356,"passed_time":0.4618529278,"remaining_time":0.8318527524},
{"learn":[4.292500657],"iteration":357,"passed_time":0.4626189909,"remaining_time":0.8296128273},
{"learn":[4.290797586],"iteration":358,"passed_time":0.4633977044,"remaining_time":0.8274037006},
{"learn":[4.286410608],"iteration":359,"passed_time":0.4642367309,"remaining_time":0.8253097437},
{"learn":[4.280278245],"iteration":360,"passed_time":0.4649862312,"remaining_time":0.8230642708},
{"learn":[4.279941283],"iteration":361,"passed_time":0.4656860133,"remaining_time":0.8207394378},
{"learn":[4.274426275],"iteration":362,"passed_time":0.4675716591,"remaining_time":0.8205045368},
{"learn":[4.273567658],"iteration":363,"passed_time":0.4692113742,"remaining_time":0.8198308626},
{"learn":[4.269488271],"iteration":364,"passed_time":0.470080308,"remaining_time":0.8178109467},
{"learn":[4.266838205],"iteration":365,"passed_time":0.470836816,"remaining_time":0.815602572},
{"learn":[4.263456509],"iteration":366,"passed_time":0.471577885,"remaining_time":0.8133754802},
{"learn":[4.260360204],"iteration":367,"passed_time":0.4722712259,"remaining_time":0.8110744967},
{"learn":[4.255120549],"iteration":368,"passed_time":0.4730648103,"remaining_time":0.8089536457},
{"learn":[4.252582211],"iteration":369,"passed_time":0.4741362648,"remaining_time":0.8073130995},
{"learn":[4.247857931],"iteration":370,"passed_time":0.474951868,"remaining_time":0.8052418463},
{"learn":[4.245288911],"iteration":371,"passed_time":0.4757206962,"remaining_time":0.8030983795},
{"learn":[4.24048515],"iteration":372,"passed_time":0.4765756709,"remaining_time":0.801107093},
{"learn":[4.2378365],"iteration":373,"passed_time":0.4775637767,"remaining_time":0.7993447171},
{"learn":[4.236751063],"iteration":374,"passed_time":0.4784245472,"remaining_time":0.7973742453},
{"learn":[4.233240093],"iteration":375,"passed_time":0.4792829291,"remaining_time":0.7954057122},
{"learn":[4.230358421],"iteration":376,"passed_time":0.4799875513,"remaining_time":0.7931889774},
{"learn":[4.225853583],"iteration":377,"passed_time":0.4807940819,"remaining_time":0.7911479338},
{"learn":[4.224702126],"iteration":378,"passed_time":0.4824318052,"remaining_time":0.7904753325},
{"learn":[4.224361982],"iteration":379,"passed_time":0.4833310118,"remaining_time":0.7885927035},
{"learn":[4.223787954],"iteration":380,"passed_time":0.4843451639,"remaining_time":0.7869019854},
{"learn":[4.22144054],"iteration":381,"passed_time":0.4851861023,"remaining_time":0.7849345844},
{"learn":[4.217739335],"iteration":382,"passed_time":0.4859289203,"remaining_time":0.782814997},
{"learn":[4.215611665],"iteration":383,"passed_time":0.4866298589,"remaining_time":0.7806353986},
{"learn":[4.210236863],"iteration":384,"passed_time":0.4873898026,"remaining_time":0.7785577367},
{"learn":[4.208454294],"iteration":385,"passed_time":0.4881356328,"remaining_time":0.7764644522},
{"learn":[4.207446501],"iteration":386,"passed_time":0.4889421676,"remaining_time":0.7744742861},
{"learn":[4.204985442],"iteration":387,"passed_time":0.4897789198,"remaining_time":0.7725378838},
{"learn":[4.202796622],"iteration":388,"passed_time":0.4905977486,"remaining_time":0.7705789831},
{"learn":[4.199774004],"iteration":389,"passed_time":0.4914956896,"remaining_time":0.7687496683},
{"learn":[4.199458358],"iteration":390,"passed_time":0.4923013142,"remaining_time":0.7667813307},
{"learn":[4.19751254],"iteration":391,"passed_time":0.4933496304,"remaining_time":0.7651953451},
{"learn":[4.195201346],"iteration":392,"passed_time":0.4941894653,"remaining_time":0.7632900902},
{"learn":[4.190593508],"iteration":393,"passed_time":0.4954678572,"remaining_time":0.7620647753},
{"learn":[4.187212054],"iteration":394,"passed_time":0.4970418326,"remaining_time":0.7612919208},
{"learn":[4.184984466],"iteration":395,"passed_time":0.4981535689,"remaining_time":0.7598099889},
{"learn":[4.182832144],"iteration":396,"passed_time":0.4990860085,"remaining_time":0.7580575897},
{"learn":[4.179752812],"iteration":397,"passed_time":0.4999563769,"remaining_time":0.7562154243},
{"learn":[4.17878934],"iteration":398,"passed_time":0.5006747807,"remaining_time":0.7541492312},
{"learn":[4.174548229],"iteration":399,"passed_time":0.5014382023,"remaining_time":0.7521573034},
{"learn":[4.168872556],"iteration":400,"passed_time":0.5021292496,"remaining_time":0.7500633928},
{"learn":[4.163926494],"iteration":401,"passed_time":0.5028641926,"remaining_time":0.7480417592},
{"learn":[4.159485076],"iteration":402,"passed_time":0.5036290261,"remaining_time":0.7460707905},
{"learn":[4.155926102],"iteration":403,"passed_time":0.5043602896,"remaining_time":0.7440562689},
{"learn":[4.153540115],"iteration":404,"passed_time":0.5051633735,"remaining_time":0.7421535982},
{"learn":[4.150983044],"iteration":405,"passed_time":0.5059688695,"remaining_time":0.7402598732},
{"learn":[4.146539132],"iteration":406,"passed_time":0.5067290671,"remaining_time":0.7383054958},
{"learn":[4.144869174],"iteration":407,"passed_time":0.5074794332,"remaining_time":0.736342707},
{"learn":[4.142825962],"iteration":408,"passed_time":0.5081766099,"remaining_time":0.7343089888},
{"learn":[4.142467378],"iteration":409,"passed_time":0.5088642281,"remaining_time":0.7322680356},
{"learn":[4.141800768],"iteration":410,"passed_time":0.51068374,"remaining_time":0.7318557734},
{"learn":[4.140107084],"iteration":411,"passed_time":0.5117368619,"remaining_time":0.7303429},
{"learn":[4.136243196],"iteration":412,"passed_time":0.5128256717,"remaining_time":0.7288829765},
{"learn":[4.133618439],"iteration":413,"passed_time":0.5139551272,"remaining_time":0.7274823781},
{"learn":[4.131053025],"iteration":414,"passed_time":0.5148229826,"remaining_time":0.7257143249},
{"learn":[4.128379975],"iteration":415,"passed_time":0.5155865756,"remaining_time":0.7238042312},
{"learn":[4.127068571],"iteration":416,"passed_time":0.5163165087,"remaining_time":0.7218525769},
{"learn":[4.125969877],"iteration":417,"passed_time":0.5169926204,"remaining_time":0.7198318304},
{"learn":[4.123893633],"iteration":418,"passed_time":0.5177868461,"remaining_time":0.717981283},
{"learn":[4.119643722],"iteration":419,"passed_time":0.5185713317,"remaining_time":0.7161223152},
{"learn":[4.11465686],"iteration":420,"passed_time":0.5193074816,"remaining_time":0.7142019759},
{"learn":[4.111565986],"iteration":421,"passed_time":0.5200238045,"remaining_time":0.7122600924},
{"learn":[4.106322452],"iteration":422,"passed_time":0.5207453071,"remaining_time":0.710331069},
{"learn":[4.104222175],"iteration":423,"passed_time":0.5214798492,"remaining_time":0.7084254555},
{"learn":[4.103008002],"iteration":424,"passed_time":0.5221824291,"remaining_time":0.70648211},
{"learn":[4.099176337],"iteration":425,"passed_time":0.5228970863,"remaining_time":0.7045608627},
{"learn":[4.096525716],"iteration":426,"passed_time":0.5236874122,"remaining_time":0.7027468084},
{"learn":[4.094967724],"iteration":427,"passed_time":0.5253640036,"remaining_time":0.7021219861},
{"learn":[4.094683584],"iteration":428,"passed_time":0.5264393578,"remaining_time":0.7006920124},
{"learn":[4.091096563],"iteration":429,"passed_time":0.5272865358,"remaining_time":0.6989612218},
{"learn":[4.089178677],"iteration":430,"passed_time":0.5280796595,"remaining_time":0.69716317},
{"learn":[4.085335077],"iteration":431,"passed_time":0.528799672,"remaining_time":0.6952736428},
{"learn":[4.084852122],"iteration":432,"passed_time":0.5295456064,"remaining_time":0.6934234615},
{"learn":[4.080322952],"iteration":433,"passed_time":0.5302681561,"remaining_time":0.6915478718},
{"learn":[4.077449519],"iteration":434,"passed_time":0.5310156378,"remaining_time":0.6897099663},
{"learn":[4.076568374],"iteration":435,"passed_time":0.5317138516,"remaining_time":0.6878133309},
{"learn":[4.076071793],"iteration":436,"passed_time":0.5324152271,"remaining_time":0.6859262537},
{"learn":[4.075027644],"iteration":437,"passed_time":0.5331358203,"remaining_time":0.6840692489},
{"learn":[4.07020837],"iteration":438,"passed_time":0.5338337929,"remaining_time":0.6821885144},
{"learn":[4.06833694],"iteration":439,"passed_time":0.5346569946,"remaining_time":0.6804725386},
{"learn":[4.063936568],"iteration":440,"passed_time":0.5354318395,"remaining_time":0.6786993159},
{"learn":[4.061734926],"iteration":441,"passed_time":0.5361646175,"remaining_time":0.6768775036},
{"learn":[4.060815619],"iteration":442,"passed_time":0.5368449794,"remaining_time":0.6749947032},
{"learn":[4.056407489],"iteration":443,"passed_time":0.5376235744,"remaining_time":0.6732403319},
{"learn":[4.05238936],"iteration":444,"passed_time":0.5393388667,"remaining_time":0.6726585865},
{"learn":[4.049685254],"iteration":445,"passed_time":0.5402242681,"remaining_time":0.6710409071},
{"learn":[4.045162016],"iteration":446,"passed_time":0.5412422097,"remaining_time":0.6695904743},
{"learn":[4.042955482],"iteration":447,"passed_time":0.5420667898,"remaining_time":0.6679037231},
{"learn":[4.041467663],"iteration":448,"passed_time":0.5427659264,"remaining_time":0.6660668718},
{"learn":[4.038920476],"iteration":449,"passed_time":0.5434454201,"remaining_time":0.664211069},
{"learn":[4.036694383],"iteration":450,"passed_time":0.5441966375,"remaining_time":0.6624477915},
{"learn":[4.034999007],"iteration":451,"passed_time":0.5449657161,"remaining_time":0.6607106469},
{"learn":[4.031928018],"iteration":452,"passed_time":0.5457129632,"remaining_time":0.6589514148},
{"learn":[4.028718143],"iteration":453,"passed_time":0.5464239157,"remaining_time":0.6571529911},
{"learn":[4.027401978],"iteration":454,"passed_time":0.5471190291,"remaining_time":0.6553403755},
{"learn":[4.025930598],"iteration":455,"passed_time":0.5478509112,"remaining_time":0.6535765256},
{"learn":[4.021074523],"iteration":456,"passed_time":0.5486409942,"remaining_time":0.6518863454},
{"learn":[4.020268486],"iteration":457,"passed_time":0.5493099218,"remaining_time":0.6500567197},
{"learn":[4.017986361],"iteration":458,"passed_time":0.5500451388,"remaining_time":0.6483102834},
{"learn":[4.014814804],"iteration":459,"passed_time":0.5507356213,"remaining_time":0.6465157294},
{"learn":[4.009704796],"iteration":460,"passed_time":0.5514472705,"remaining_time":0.6447507132},
{"learn":[4.008440457],"iteration":461,"passed_time":0.5521864754,"remaining_time":0.6430223458},
{"learn":[4.004854849],"iteration":462,"passed_time":0.5537512563,"remaining_time":0.6422557767},
{"learn":[4.000898028],"iteration":463,"passed_time":0.5547903334,"remaining_time":0.6408784886},
{"learn":[3.996617985],"iteration":464,"passed_time":0.5557813236,"remaining_time":0.6394473293},
{"learn":[3.995443319],"iteration":465,"passed_time":0.556608135,"remaining_time":0.637829923},
{"learn":[3.990771995],"iteration":466,"passed_time":0.5574121232,"remaining_time":0.6361898537},
{"learn":[3.989249359],"iteration":467,"passed_time":0.5581376759,"remaining_time":0.6344641957},
{"learn":[3.986599538],"iteration":468,"passed_time":0.5588730635,"remaining_time":0.6327539376},
{"learn":[3.985628919],"iteration":469,"passed_time":0.5595761805,"remaining_time":0.6310114376},
{"learn":[3.985086112],"iteration":470,"passed_time":0.5604069176,"remaining_time":0.6294166867},
{"learn":[3.98466839],"iteration":471,"passed_time":0.5612114068,"remaining_time":0.627795811},
{"learn":[3.984233894],"iteration":472,"passed_time":0.5618568035,"remaining_time":0.6260011321},
{"learn":[3.981855845],"iteration":473,"passed_time":0.562565907,"remaining_time":0.6242819981},
{"learn":[3.978684264],"iteration":474,"passed_time":0.5632374207,"remaining_time":0.6225255702},
{"learn":[3.974361269],"iteration":475,"passed_time":0.5640459061,"remaining_time":0.6209244849},
{"learn":[3.972074049],"iteration":476,"passed_time":0.5648424034,"remaining_time":0.6193135786},
{"learn":[3.97191982],"iteration":477,"passed_time":0.5654939413,"remaining_time":0.617547777},
{"learn":[3.969616848],"iteration":478,"passed_time":0.5661865426,"remaining_time":0.6158312917},
{"learn":[3.968533527],"iteration":479,"passed_time":0.5668882611,"remaining_time":0.6141289495},
{"learn":[3.967568753],"iteration":480,"passed_time":0.5685704768,"remaining_time":0.6134887265},
{"learn":[3.966232553],"iteration":481,"passed_time":0.5695962093,"remaining_time":0.6121386648},
{"learn":[3.961522393],"iteration":482,"passed_time":0.5705995003,"remaining_time":0.6107659247},
{"learn":[3.955829553],"iteration":483,"passed_time":0.5714686752,"remaining_time":0.6092517281},
{"learn":[3.954248095],"iteration":484,"passed_time":0.5721584686,"remaining_time":0.6075497141},
{"learn":[3.951922606],"iteration":485,"passed_time":0.5728557587,"remaining_time":0.6058597942},
{"learn":[3.94978202],"iteration":486,"passed_time":0.5736118802,"remaining_time":0.6042359231},
{"learn":[3.949518999],"iteration":487,"passed_time":0.5743010113,"remaining_time":0.6025453233},
{"learn":[3.945431216],"iteration":488,"passed_time":0.5750787691,"remaining_time":0.6009514336},
{"learn":[3.943249086],"iteration":489,"passed_time":0.5757453796,"remaining_time":0.599245191},
{"learn":[3.941981548],"iteration":490,"passed_time":0.5764426647,"remaining_time":0.5975749824},
{"learn":[3.936600517],"iteration":491,"passed_time":0.5770801638,"remaining_time":0.5958469984},
{"learn":[3.934476885],"iteration":492,"passed_time":0.5778313291,"remaining_time":0.5942403324},
{"learn":[3.93045798],"iteration":493,"passed_time":0.5785545941,"remaining_time":0.5926085519},
{"learn":[3.925977375],"iteration":494,"passed_time":0.5792620713,"remaining_time":0.5909643354},
{"learn":[3.92457993],"iteration":495,"passed_time":0.5799384343,"remaining_time":0.5892922801},
{"learn":[3.919849146],"iteration":496,"passed_time":0.5806128921,"remaining_time":0.5876223032},
{"learn":[3.919681964],"iteration":497,"passed_time":0.581394569,"remaining_time":0.5860644049},
{"learn":[3.917633027],"iteration":498,"passed_time":0.5834186196,"remaining_time":0.5857569707},
{"learn":[3.916616419],"iteration":499,"passed_time":0.5843639197,"remaining_time":0.5843639197},
{"learn":[3.912896166],"iteration":500,"passed_time":0.5852410074,"remaining_time":0.582904716},
{"learn":[3.912769674],"iteration":501,"passed_time":0.5859126724,"remaining_time":0.5812440455},
{"learn":[3.909373788],"iteration":502,"passed_time":0.5866532321,"remaining_time":0.5796553804},
{"learn":[3.906706036],"iteration":503,"passed_time":0.5874264894,"remaining_time":0.5781022594},
{"learn":[3.903895664],"iteration":504,"passed_time":0.5881479869,"remaining_time":0.5765014921},
{"learn":[3.902982967],"iteration":505,"passed_time":0.5888224026,"remaining_time":0.574858235},
{"learn":[3.900905528],"iteration":506,"passed_time":0.5894780654,"remaining_time":0.5732005646},
{"learn":[3.897463465],"iteration":507,"passed_time":0.5902495519,"remaining_time":0.5716590148},
{"learn":[3.895918033],"iteration":508,"passed_time":0.5909609666,"remaining_time":0.5700625434},
{"learn":[3.893921936],"iteration":509,"passed_time":0.5916836307,"remaining_time":0.568480351},
{"learn":[3.890237934],"iteration":510,"passed_time":0.5924102676,"remaining_time":0.5669053245},
{"learn":[3.887311613],"iteration":511,"passed_time":0.5930868491,"remaining_time":0.565285903},
{"learn":[3.884869735],"iteration":512,"passed_time":0.5939356785,"remaining_time":0.5638336753},
{"learn":[3.882101231],"iteration":513,"passed_time":0.5946729092,"remaining_time":0.562278276},
{"learn":[3.88060368],"iteration":514,"passed_time":0.5953673276,"remaining_time":0.5606857357},
{"learn":[3.877726076],"iteration":515,"passed_time":0.596358206,"remaining_time":0.5593747513},
{"learn":[3.874938145],"iteration":516,"passed_time":0.5974844736,"remaining_time":0.5581914908},
{"learn":[3.874340833],"iteration":517,"passed_time":0.5982793556,"remaining_time":0.5567000954},
{"learn":[3.873105224],"iteration":518,"passed_time":0.599129576,"remaining_time":0.5552626706},
{"learn":[3.869800236],"iteration":519,"passed_time":0.5998524888,"remaining_time":0.5537099897},
{"learn":[3.867932518],"iteration":520,"passed_time":0.6005616763,"remaining_time":0.5521478752},
{"learn":[3.866666962],"iteration":521,"passed_time":0.6012464926,"remaining_time":0.5505667116},
{"learn":[3.865527652],"iteration":522,"passed_time":0.6019589503,"remaining_time":0.549014186},
{"learn":[3.861900081],"iteration":523,"passed_time":0.6027031197,"remaining_time":0.5474936736},
{"learn":[3.858502887],"iteration":524,"passed_time":0.6034120912,"remaining_time":0.545944273},
{"learn":[3.858335097],"iteration":525,"passed_time":0.6040784538,"remaining_time":0.5443596713},
{"learn":[3.855719306],"iteration":526,"passed_time":0.6047819809,"remaining_time":0.5428119107},
{"learn":[3.855137428],"iteration":527,"passed_time":0.605566796,"remaining_time":0.5413400146},
{"learn":[3.851985706],"iteration":528,"passed_time":0.6063383841,"remaining_time":0.5398589394},
{"learn":[3.851051809],"iteration":529,"passed_time":0.6070075941,"remaining_time":0.5382897533},
{"learn":[3.850679146],"iteration":530,"passed_time":0.6076766604,"remaining_time":0.53672383},
{"learn":[3.848179484],"iteration":531,"passed_time":0.6083301061,"remaining_time":0.5351475369},
{"learn":[3.844551071],"iteration":532,"passed_time":0.6089940666,"remaining_time":0.5335839196},
{"learn":[3.841604794],"iteration":533,"passed_time":0.6097550148,"remaining_time":0.5321083088},
{"learn":[3.83969656],"iteration":534,"passed_time":0.6113099044,"remaining_time":0.5313254309},
{"learn":[3.836811463],"iteration":535,"passed_time":0.6122309795,"remaining_time":0.5299909972},
{"learn":[3.834182551],"iteration":536,"passed_time":0.6130505093,"remaining_time":0.5285705508},
{"learn":[3.828012842],"iteration":537,"passed_time":0.6137693106,"remaining_time":0.5270658392},
{"learn":[3.826636176],"iteration":538,"passed_time":0.6144610891,"remaining_time":0.5255409315},
{"learn":[3.826189798],"iteration":539,"passed_time":0.6151638447,"remaining_time":0.5240284603},
{"learn":[3.824104738],"iteration":540,"passed_time":0.6158723775,"remaining_time":0.5225238841},
{"learn":[3.82300218],"iteration":541,"passed_time":0.6166440405,"remaining_time":0.5210755914},
{"learn":[3.817146402],"iteration":542,"passed_time":0.6173376167,"remaining_time":0.5195640715},
{"learn":[3.814638044],"iteration":543,"passed_time":0.6180405118,"remaining_time":0.5180633702},
{"learn":[3.812979573],"iteration":544,"passed_time":0.6187261172,"remaining_time":0.5165511621},
{"learn":[3.811938825],"iteration":545,"passed_time":0.6194630319,"remaining_time":0.5150846456},
{"learn":[3.811479418],"iteration":546,"passed_time":0.6201515184,"remaining_time":0.5135806907},
{"learn":[3.80742981],"iteration":547,"passed_time":0.6208495968,"remaining_time":0.5120876237},
{"learn":[3.805097043],"iteration":548,"passed_time":0.6215641716,"remaining_time":0.5106110044},
{"learn":[3.801577232],"iteration":549,"passed_time":0.622280508,"remaining_time":0.5091385974},
{"learn":[3.799762083],"iteration":550,"passed_time":0.62296059,"remaining_time":0.5076393918},
{"learn":[3.796393455],"iteration":551,"passed_time":0.6236591879,"remaining_time":0.5061581815},
{"learn":[3.793486459],"iteration":552,"passed_time":0.6243428493,"remaining_time":0.5046677281},
{"learn":[3.792006091],"iteration":553,"passed_time":0.6261413643,"remaining_time":0.5040777049},
{"learn":[3.78932128],"iteration":554,"passed_time":0.6271582688,"remaining_time":0.50285663},
{"learn":[3.787581812],"iteration":555,"passed_time":0.6279823521,"remaining_time":0.50148231},
{"learn":[3.785308865],"iteration":556,"passed_time":0.628714931,"remaining_time":0.5000371893},
{"learn":[3.78465475],"iteration":557,"passed_time":0.6293771417,"remaining_time":0.4985388829},
{"learn":[3.780498869],"iteration":558,"passed_time":0.6300839482,"remaining_time":0.4970787499},
{"learn":[3.778734909],"iteration":559,"passed_time":0.6308658764,"remaining_time":0.4956803315},
{"learn":[3.778652349],"iteration":560,"passed_time":0.6315544948,"remaining_time":0.4942110931},
{"learn":[3.777928006],"iteration":561,"passed_time":0.632283464,"remaining_time":0.4927760804},
{"learn":[3.776131406],"iteration":562,"passed_time":0.6329449897,"remaining_time":0.4912912265},
{"learn":[3.772925617],"iteration":563,"passed_time":0.6336842224,"remaining_time":0.4898693634},
{"learn":[3.7727745],"iteration":564,"passed_time":0.634323383,"remaining_time":0.4883728701},
{"learn":[3.771763073],"iteration":565,"passed_time":0.6350185393,"remaining_time":0.4869223428},
{"learn":[3.768738162],"iteration":566,"passed_time":0.6358051588,"remaining_time":0.4855443276},
{"learn":[3.767220794],"iteration":567,"passed_time":0.6364957145,"remaining_time":0.4840953321},
{"learn":[3.766691102],"iteration":568,"passed_time":0.6372082285,"remaining_time":0.4826656353},
{"learn":[3.766259335],"iteration":569,"passed_time":0.6378810952,"remaining_time":0.4812085455},
{"learn":[3.76116362],"iteration":570,"passed_time":0.6385400442,"remaining_time":0.479743746},
{"learn":[3.758633056],"iteration":571,"passed_time":0.6393106625,"remaining_time":0.4783653209},
{"learn":[3.754603809],"iteration":572,"passed_time":0.6409059449,"remaining_time":0.4776035575},
{"learn":[3.754070549],"iteration":573,"passed_time":0.641634013,"remaining_time":0.4761952779},
{"learn":[3.750534319],"iteration":574,"passed_time":0.6423400514,"remaining_time":0.4747730814},
{"learn":[3.746491516],"iteration":575,"passed_time":0.643104963,"remaining_time":0.4733967089},
{"learn":[3.744210544],"iteration":576,"passed_time":0.6439520897,"remaining_time":0.4720827278},
{"learn":[3.742929991],"iteration":577,"passed_time":0.6446857107,"remaining_time":0.4706874912},
{"learn":[3.740402992],"iteration":578,"passed_time":0.6453645488,"remaining_time":0.4692547065},
{"learn":[3.739644243],"iteration":579,"passed_time":0.6460880576,"remaining_time":0.4678568693},
{"learn":[3.737529404],"iteration":580,"passed_time":0.6468027929,"remaining_time":0.4664550262},
{"learn":[3.737196923],"iteration":581,"passed_time":0.6475574704,"remaining_time":0.4650842313},
{"learn":[3.733954464],"iteration":582,"passed_time":0.6482301195,"remaining_time":0.4636568779},
{"learn":[3.731608623],"iteration":583,"passed_time":0.6489178042,"remaining_time":0.4622428194},
{"learn":[3.729843952],"iteration":584,"passed_time":0.6496637226,"remaining_time":0.4608725553},
{"learn":[3.727223798],"iteration":585,"passed_time":0.6503591141,"remaining_time":0.4594687257},
{"learn":[3.725351667],"iteration":586,"passed_time":0.6511201623,"remaining_time":0.4581135043},
{"learn":[3.725026912],"iteration":587,"passed_time":0.6517957227,"remaining_time":0.4567004043},
{"learn":[3.721974565],"iteration":588,"passed_time":0.6524809978,"remaining_time":0.4552965876},
{"learn":[3.720269493],"iteration":589,"passed_time":0.6533172306,"remaining_time":0.4540001094},
{"learn":[3.718907466],"iteration":590,"passed_time":0.6547803376,"remaining_time":0.4531390153},
{"learn":[3.715602912],"iteration":591,"passed_time":0.6556265003,"remaining_time":0.4518506961},
{"learn":[3.714463059],"iteration":592,"passed_time":0.6563860625,"remaining_time":0.4505044307},
{"learn":[3.710802077],"iteration":593,"passed_time":0.657123394,"remaining_time":0.4491449461},
{"learn":[3.708032435],"iteration":594,"passed_time":0.6578409415,"remaining_time":0.4477740862},
{"learn":[3.703788939],"iteration":595,"passed_time":0.6585026605,"remaining_time":0.4463675753},
{"learn":[3.702500944],"iteration":596,"passed_time":0.6591729496,"remaining_time":0.4449693446},
{"learn":[3.698196925],"iteration":597,"passed_time":0.6599521195,"remaining_time":0.4436467425},
{"learn":[3.69658891],"iteration":598,"passed_time":0.6606420709,"remaining_time":0.4422662277},
{"learn":[3.696124066],"iteration":599,"passed_time":0.6613692263,"remaining_time":0.4409128175},
{"learn":[3.693537052],"iteration":600,"passed_time":0.6620669837,"remaining_time":0.4395419742},
{"learn":[3.691343275],"iteration":601,"passed_time":0.6627714067,"remaining_time":0.4381777739},
{"learn":[3.690973831],"iteration":602,"passed_time":0.6634609505,"remaining_time":0.4368059657},
{"learn":[3.686151073],"iteration":603,"passed_time":0.6641603838,"remaining_time":0.4354429006},
{"learn":[3.683921982],"iteration":604,"passed_time":0.6648987911,"remaining_time":0.4341074752},
{"learn":[3.679975271],"iteration":605,"passed_time":0.6655828224,"remaining_time":0.4327386667},
{"learn":[3.674047638],"iteration":606,"passed_time":0.6662749211,"remaining_time":0.4313773377},
{"learn":[3.673151794],"iteration":607,"passed_time":0.6669681308,"remaining_time":0.4300189265},
{"learn":[3.670953108],"iteration":608,"passed_time":0.6676498483,"remaining_time":0.4286553214},
{"learn":[3.6703947],"iteration":609,"passed_time":0.6689167496,"remaining_time":0.4276680858},
{"learn":[3.668433805],"iteration":610,"passed_time":0.6701679539,"remaining_time":0.4266699412},
{"learn":[3.668304956],"iteration":611,"passed_time":0.6709561888,"remaining_time":0.425377453},
{"learn":[3.667880012],"iteration":612,"passed_time":0.6716515384,"remaining_time":0.4240279696},
{"learn":[3.667282264],"iteration":613,"passed_time":0.6723491622,"remaining_time":0.4226820466},
{"learn":[3.664611483],"iteration":614,"passed_time":0.6731380988,"remaining_time":0.4213953952},
{"learn":[3.662543394],"iteration":615,"passed_time":0.6738468283,"remaining_time":0.4200603605},
{"learn":[3.659041959],"iteration":616,"passed_time":0.6745560083,"remaining_time":0.4187276356},
{"learn":[3.656868545],"iteration":617,"passed_time":0.6752997003,"remaining_time":0.4174182614},
{"learn":[3.654785614],"iteration":618,"passed_time":0.6759787141,"remaining_time":0.4160709048},
{"learn":[3.654566096],"iteration":619,"passed_time":0.6766752958,"remaining_time":0.4147364716},
{"learn":[3.651007045],"iteration":620,"passed_time":0.6774712687,"remaining_time":0.4134647517},
{"learn":[3.648921786],"iteration":621,"passed_time":0.6781507371,"remaining_time":0.4121237599},
{"learn":[3.647655706],"iteration":622,"passed_time":0.6788418071,"remaining_time":0.4107919122},
{"learn":[3.647241144],"iteration":623,"passed_time":0.6795200166,"remaining_time":0.409454369},
{"learn":[3.644195689],"iteration":624,"passed_time":0.6802394593,"remaining_time":0.4081436756},
{"learn":[3.642632246],"iteration":625,"passed_time":0.6809659222,"remaining_time":0.4068390653},
{"learn":[3.642523322],"iteration":626,"passed_time":0.681507059,"remaining_time":0.4054260494},
{"learn":[3.641494659],"iteration":627,"passed_time":0.6821793542,"remaining_time":0.4040935028},
{"learn":[3.63976496],"iteration":628,"passed_time":0.6839331768,"remaining_time":0.4034009675},
{"learn":[3.637945652],"iteration":629,"passed_time":0.6847157597,"remaining_time":0.4021346525},
{"learn":[3.636233667],"iteration":630,"passed_time":0.6854521146,"remaining_time":0.4008428372},
{"learn":[3.635304404],"iteration":631,"passed_time":0.6861084078,"remaining_time":0.3995061615},
{"learn":[3.632234951],"iteration":632,"passed_time":0.686850661,"remaining_time":0.3982214733},
{"learn":[3.631630987],"iteration":633,"passed_time":0.6875909896,"remaining_time":0.3969373852},
{"learn":[3.630301009],"iteration":634,"passed_time":0.6884473746,"remaining_time":0.3957217193},
{"learn":[3.629077964],"iteration":635,"passed_time":0.6893597284,"remaining_time":0.3945392156},
{"learn":[3.628004522],"iteration":636,"passed_time":0.6901354179,"remaining_time":0.3932796809},
{"learn":[3.625062876],"iteration":637,"passed_time":0.6908465738,"remaining_time":0.3919850466},
{"learn":[3.624917986],"iteration":638,"passed_time":0.6915972533,"remaining_time":0.3907145672},
{"learn":[3.622887087],"iteration":639,"passed_time":0.692377767,"remaining_time":0.389462494},
{"learn":[3.621220865],"iteration":640,"passed_time":0.6930475435,"remaining_time":0.3881498722},
{"learn":[3.621143844],"iteration":641,"passed_time":0.6936778475,"remaining_time":0.3868172421},
{"learn":[3.620822821],"iteration":642,"passed_time":0.6943368393,"remaining_time":0.3855027242},
{"learn":[3.619202826],"iteration":643,"passed_time":0.6950566383,"remaining_time":0.384223856},
{"learn":[3.618204882],"iteration":644,"passed_time":0.6957595124,"remaining_time":0.382937406},
{"learn":[3.614259666],"iteration":645,"passed_time":0.6964467592,"remaining_time":0.3816441993},
{"learn":[3.613415661],"iteration":646,"passed_time":0.6977846396,"remaining_time":0.3807078482},
{"learn":[3.611096773],"iteration":647,"passed_time":0.6989028608,"remaining_time":0.3796509367},
{"learn":[3.610820695],"iteration":648,"passed_time":0.6997951338,"remaining_time":0.3784716363},
{"learn":[3.609290065],"iteration":649,"passed_time":0.7005968234,"remaining_time":0.3772444434},
{"learn":[3.60897947],"iteration":650,"passed_time":0.7012699414,"remaining_time":0.3759496307},
{"learn":[3.606570702],"iteration":651,"passed_time":0.7019378134,"remaining_time":0.374653925},
{"learn":[3.606292637],"iteration":652,"passed_time":0.7027087469,"remaining_time":0.3734149084},
{"learn":[3.602753838],"iteration":653,"passed_time":0.7033451139,"remaining_time":0.3721061306},
{"learn":[3.599755869],"iteration":654,"passed_time":0.7040648969,"remaining_time":0.3708433426},
{"learn":[3.599509575],"iteration":655,"passed_time":0.7047575242,"remaining_time":0.36956797},
{"learn":[3.595337722],"iteration":656,"passed_time":0.7055299293,"remaining_time":0.3683360209},
{"learn":[3.595168561],"iteration":657,"passed_time":0.7061938008,"remaining_time":0.3670490576},
{"learn":[3.59290559],"iteration":658,"passed_time":0.7069110129,"remaining_time":0.3657915863},
{"learn":[3.592015928],"iteration":659,"passed_time":0.7076026065,"remaining_time":0.3645225549},
{"learn":[3.590680403],"iteration":660,"passed_time":0.7082790603,"remaining_time":0.363247506},
{"learn":[3.590361532],"iteration":661,"passed_time":0.7089838758,"remaining_time":0.3619887462},
{"learn":[3.589069739],"iteration":662,"passed_time":0.7097639802,"remaining_time":0.3607699266},
{"learn":[3.585010186],"iteration":663,"passed_time":0.7104430461,"remaining_time":0.3595013004},
{"learn":[3.582997552],"iteration":664,"passed_time":0.7119293998,"remaining_time":0.3586411262},
{"learn":[3.582119256],"iteration":665,"passed_time":0.7132686056,"remaining_time":0.3577052767},
{"learn":[3.579019356],"iteration":666,"passed_time":0.7140035133,"remaining_time":0.3564665216},
{"learn":[3.57719559],"iteration":667,"passed_time":0.7148029825,"remaining_time":0.3552613625},
{"learn":[3.574050046],"iteration":668,"passed_time":0.7155135903,"remaining_time":0.3540134505},
{"learn":[3.572204518],"iteration":669,"passed_time":0.7163417775,"remaining_time":0.3528250546},
{"learn":[3.569508025],"iteration":670,"passed_time":0.7170373599,"remaining_time":0.3515727145},
{"learn":[3.566268704],"iteration":671,"passed_time":0.7178150052,"remaining_time":0.3503620859},
{"learn":[3.562564052],"iteration":672,"passed_time":0.7185075426,"remaining_time":0.3491113914},
{"learn":[3.561173586],"iteration":673,"passed_time":0.7192125455,"remaining_time":0.3478683826},
{"learn":[3.559551904],"iteration":674,"passed_time":0.7199157751,"remaining_time":0.3466261139},
{"learn":[3.558593054],"iteration":675,"passed_time":0.7206344302,"remaining_time":0.3453928334},
{"learn":[3.555647008],"iteration":676,"passed_time":0.7213092721,"remaining_time":0.3441401697},
{"learn":[3.553100059],"iteration":677,"passed_time":0.7220482669,"remaining_time":0.3429196784},
{"learn":[3.55085578],"iteration":678,"passed_time":0.722834994,"remaining_time":0.3417231709},
{"learn":[3.550737965],"iteration":679,"passed_time":0.7234876984,"remaining_time":0.3404647993},
{"learn":[3.549408772],"iteration":680,"passed_time":0.7242197974,"remaining_time":0.339245397},
{"learn":[3.547390589],"iteration":681,"passed_time":0.7262299226,"remaining_time":0.3386233363},
{"learn":[3.54723575],"iteration":682,"passed_time":0.7272514286,"remaining_time":0.3375383644},
{"learn":[3.543988891],"iteration":683,"passed_time":0.7282362356,"remaining_time":0.3364366234},
{"learn":[3.543868508],"iteration":684,"passed_time":0.7290052427,"remaining_time":0.3352359875},
{"learn":[3.542752124],"iteration":685,"passed_time":0.7297829956,"remaining_time":0.3340406131},
{"learn":[3.541334315],"iteration":686,"passed_time":0.7305718137,"remaining_time":0.3328514959},
{"learn":[3.540208266],"iteration":687,"passed_time":0.7313357774,"remaining_time":0.3316522711},
{"learn":[3.537730983],"iteration":688,"passed_time":0.7321267765,"remaining_time":0.330466513},
{"learn":[3.53419867],"iteration":689,"passed_time":0.7329461163,"remaining_time":0.329294632},
{"learn":[3.532628335],"iteration":690,"passed_time":0.7336882645,"remaining_time":0.3280892529},
{"learn":[3.532204987],"iteration":691,"passed_time":0.7345029424,"remaining_time":0.3269174946},
{"learn":[3.530618147],"iteration":692,"passed_time":0.7352292388,"remaining_time":0.3257076137},
{"learn":[3.528909306],"iteration":693,"passed_time":0.7359525072,"remaining_time":0.3244977914},
{"learn":[3.526700678],"iteration":694,"passed_time":0.7368320785,"remaining_time":0.3233579625},
{"learn":[3.526439574],"iteration":695,"passed_time":0.737577106,"remaining_time":0.3221601153},
{"learn":[3.525784216],"iteration":696,"passed_time":0.7383898299,"remaining_time":0.3209929963},
{"learn":[3.524112693],"iteration":697,"passed_time":0.7400197395,"remaining_time":0.3201804603},
{"learn":[3.522813541],"iteration":698,"passed_time":0.7410347227,"remaining_time":0.319100789},
{"learn":[3.519148203],"iteration":699,"passed_time":0.7418317974,"remaining_time":0.3179279132},
{"learn":[3.517236747],"iteration":700,"passed_time":0.7426513911,"remaining_time":0.3167657146},
{"learn":[3.515603888],"iteration":701,"passed_time":0.743393314,"remaining_time":0.3155715208},
{"learn":[3.51263524],"iteration":702,"passed_time":0.7441335384,"remaining_time":0.314377896},
{"learn":[3.51123442],"iteration":703,"passed_time":0.7448932182,"remaining_time":0.3131937395},
{"learn":[3.50828027],"iteration":704,"passed_time":0.7456384466,"remaining_time":0.3120047401},
{"learn":[3.508265537],"iteration":705,"passed_time":0.7460932032,"remaining_time":0.3106960364},
{"learn":[3.506774876],"iteration":706,"passed_time":0.7467663632,"remaining_time":0.3094802609},
{"learn":[3.50552068],"iteration":707,"passed_time":0.7475102898,"remaining_time":0.3082952043},
{"learn":[3.501973993],"iteration":708,"passed_time":0.7481661526,"remaining_time":0.3070752474},
{"learn":[3.498880354],"iteration":709,"passed_time":0.7488897546,"remaining_time":0.3058845477},
{"learn":[3.497370959],"iteration":710,"passed_time":0.7495598513,"remaining_time":0.3046734135},
{"learn":[3.496050455],"iteration":711,"passed_time":0.7502281847,"remaining_time":0.3034630859},
{"learn":[3.495630067],"iteration":712,"passed_time":0.7508937564,"remaining_time":0.302253167},
{"learn":[3.49550669],"iteration":713,"passed_time":0.751542367,"remaining_time":0.3010379789},
{"learn":[3.493652375],"iteration":714,"passed_time":0.7524879268,"remaining_time":0.2999427401},
{"learn":[3.491915684],"iteration":715,"passed_time":0.7545263263,"remaining_time":0.299281392},
{"learn":[3.490303956],"iteration":716,"passed_time":0.7553385257,"remaining_time":0.2981322215},
{"learn":[3.488363853],"iteration":717,"passed_time":0.7561430544,"remaining_time":0.2969809768},
{"learn":[3.485483936],"iteration":718,"passed_time":0.7568093152,"remaining_time":0.2957766587},
{"learn":[3.483763466],"iteration":719,"passed_time":0.7575340569,"remaining_time":0.2945965777},
{"learn":[3.481642352],"iteration":720,"passed_time":0.758239175,"remaining_time":0.2934101662},
{"learn":[3.479826119],"iteration":721,"passed_time":0.7589312938,"remaining_time":0.2922200827},
{"learn":[3.478588728],"iteration":722,"passed_time":0.7596067416,"remaining_time":0.2910249895},
{"learn":[3.475390887],"iteration":723,"passed_time":0.7602738555,"remaining_time":0.2898281549},
{"learn":[3.472636852],"iteration":724,"passed_time":0.7610446032,"remaining_time":0.2886720909},
{"learn":[3.47061883],"iteration":725,"passed_time":0.7617734665,"remaining_time":0.2875012807},
{"learn":[3.46953149],"iteration":726,"passed_time":0.7624208198,"remaining_time":0.2863010781},
{"learn":[3.467217162],"iteration":727,"passed_time":0.7632222337,"remaining_time":0.2851599555},
{"learn":[3.465686216],"iteration":728,"passed_time":0.7639555505,"remaining_time":0.2839944502},
{"learn":[3.462631216],"iteration":729,"passed_time":0.7646286223,"remaining_time":0.2828078466},
{"learn":[3.461451053],"iteration":730,"passed_time":0.7652889883,"remaining_time":0.2816179724},
{"learn":[3.458950469],"iteration":731,"passed_time":0.7659682264,"remaining_time":0.2804364545},
{"learn":[3.458072145],"iteration":732,"passed_time":0.766716778,"remaining_time":0.2792815549},
{"learn":[3.454364268],"iteration":733,"passed_time":0.7694332996,"remaining_time":0.2788409505},
{"learn":[3.453243406],"iteration":734,"passed_time":0.7708045247,"remaining_time":0.2779091143},
{"learn":[3.453017963],"iteration":735,"passed_time":0.7717059762,"remaining_time":0.2768075784},
{"learn":[3.45201581],"iteration":736,"passed_time":0.7725101703,"remaining_time":0.275671879},
{"learn":[3.449510107],"iteration":737,"passed_time":0.7733429733,"remaining_time":0.2745472344},
{"learn":[3.447189189],"iteration":738,"passed_time":0.7741203799,"remaining_time":0.2734038148},
{"learn":[3.446423605],"iteration":739,"passed_time":0.7748622288,"remaining_time":0.2722488912},
{"learn":[3.445531987],"iteration":740,"passed_time":0.7756181326,"remaining_time":0.2710999951},
{"learn":[3.445328199],"iteration":741,"passed_time":0.7763148857,"remaining_time":0.269931591},
{"learn":[3.443327544],"iteration":742,"passed_time":0.7770185481,"remaining_time":0.2687668464},
{"learn":[3.441475798],"iteration":743,"passed_time":0.7777764042,"remaining_time":0.2676219885},
{"learn":[3.439046501],"iteration":744,"passed_time":0.7784910613,"remaining_time":0.2664633834},
{"learn":[3.435899469],"iteration":745,"passed_time":0.7791902963,"remaining_time":0.2653007175},
{"learn":[3.433988352],"iteration":746,"passed_time":0.7799143,"remaining_time":0.2641476813},
{"learn":[3.433413263],"iteration":747,"passed_time":0.7806291084,"remaining_time":0.2629926943},
{"learn":[3.429944699],"iteration":748,"passed_time":0.7814501224,"remaining_time":0.2618744736},
{"learn":[3.429291634],"iteration":749,"passed_time":0.7836601395,"remaining_time":0.2612200465},
{"learn":[3.429175603],"iteration":750,"passed_time":0.7847544786,"remaining_time":0.2601915648},
{"learn":[3.428780323],"iteration":751,"passed_time":0.7856333515,"remaining_time":0.25909185},
{"learn":[3.423893341],"iteration":752,"passed_time":0.7863296819,"remaining_time":0.2579328438},
{"learn":[3.421024316],"iteration":753,"passed_time":0.7870532671,"remaining_time":0.2567839572},
{"learn":[3.420969872],"iteration":754,"passed_time":0.7877307504,"remaining_time":0.2556212369},
{"learn":[3.419544785],"iteration":755,"passed_time":0.7884159112,"remaining_time":0.2544622782},
{"learn":[3.417057977],"iteration":756,"passed_time":0.7891994026,"remaining_time":0.2533361359},
{"learn":[3.415160245],"iteration":757,"passed_time":0.7898982955,"remaining_time":0.2521838885},
{"learn":[3.412854597],"iteration":758,"passed_time":0.7906740817,"remaining_time":0.2510572512},
{"learn":[3.410926347],"iteration":759,"passed_time":0.7914175872,"remaining_time":0.2499213433},
{"learn":[3.408963843],"iteration":760,"passed_time":0.7921158581,"remaining_time":0.2487722603},
{"learn":[3.407629634],"iteration":761,"passed_time":0.7927867011,"remaining_time":0.2476157938},
{"learn":[3.404384724],"iteration":762,"passed_time":0.7934852729,"remaining_time":0.2464692132},
{"learn":[3.403041656],"iteration":763,"passed_time":0.7942049828,"remaining_time":0.245330335},
{"learn":[3.401101731],"iteration":764,"passed_time":0.7949376096,"remaining_time":0.2441965206},
{"learn":[3.400890668],"iteration":765,"passed_time":0.7956073188,"remaining_time":0.2430445334},
{"learn":[3.399289941],"iteration":766,"passed_time":0.7970730723,"remaining_time":0.2421356269},
{"learn":[3.399202366],"iteration":767,"passed_time":0.7982960435,"remaining_time":0.2411519298},
{"learn":[3.397447845],"iteration":768,"passed_time":0.7991380056,"remaining_time":0.240053159},
{"learn":[3.394655341],"iteration":769,"passed_time":0.7999496923,"remaining_time":0.238946012},
{"learn":[3.393228229],"iteration":770,"passed_time":0.8006892477,"remaining_time":0.2378182072},
{"learn":[3.389691197],"iteration":771,"passed_time":0.8014980819,"remaining_time":0.2367118688},
{"learn":[3.389626772],"iteration":772,"passed_time":0.8023348291,"remaining_time":0.235614497},
{"learn":[3.388480222],"iteration":773,"passed_time":0.8031638198,"remaining_time":0.2345155339},
{"learn":[3.388215066],"iteration":774,"passed_time":0.8039528296,"remaining_time":0.2334056602},
{"learn":[3.386324358],"iteration":775,"passed_time":0.8047852896,"remaining_time":0.2323091558},
{"learn":[3.383913061],"iteration":776,"passed_time":0.8056714584,"remaining_time":0.2312287455},
{"learn":[3.382839768],"iteration":777,"passed_time":0.8065227546,"remaining_time":0.2301388837},
{"learn":[3.381961844],"iteration":778,"passed_time":0.8074042581,"remaining_time":0.2290582042},
{"learn":[3.381521703],"iteration":779,"passed_time":0.8082420541,"remaining_time":0.2279657076},
{"learn":[3.380918963],"iteration":780,"passed_time":0.8091338951,"remaining_time":0.226889018},
{"learn":[3.377139006],"iteration":781,"passed_time":0.8109278482,"remaining_time":0.226064285},
{"learn":[3.376004372],"iteration":782,"passed_time":0.8123035604,"remaining_time":0.2251211655},
{"learn":[3.373826468],"iteration":783,"passed_time":0.8131759602,"remaining_time":0.2240382747},
{"learn":[3.373546786],"iteration":784,"passed_time":0.8140230717,"remaining_time":0.2229489942},
{"learn":[3.372109181],"iteration":785,"passed_time":0.8148993115,"remaining_time":0.2218682604},
{"learn":[3.370764924],"iteration":786,"passed_time":0.815751891,"remaining_time":0.2207816427},
{"learn":[3.367833107],"iteration":787,"passed_time":0.8166204239,"remaining_time":0.219699911},
{"learn":[3.36450404],"iteration":788,"passed_time":0.8175134902,"remaining_time":0.2186252807},
{"learn":[3.361794558],"iteration":789,"passed_time":0.8183946836,"remaining_time":0.2175479539},
{"learn":[3.356880529],"iteration":790,"passed_time":0.8193260625,"remaining_time":0.2164843831},
{"learn":[3.353843509],"iteration":791,"passed_time":0.8202509398,"remaining_time":0.2154194387},
{"learn":[3.353640253],"iteration":792,"passed_time":0.8211171993,"remaining_time":0.2143395463},
{"learn":[3.353055088],"iteration":793,"passed_time":0.8220242817,"remaining_time":0.2132707834},
{"learn":[3.351415617],"iteration":794,"passed_time":0.822898802,"remaining_time":0.2121940307},
{"learn":[3.349169061],"iteration":795,"passed_time":0.8248350385,"remaining_time":0.2113898842},
{"learn":[3.346211014],"iteration":796,"passed_time":0.8263749043,"remaining_time":0.2104819392},
{"learn":[3.344560452],"iteration":797,"passed_time":0.8274310282,"remaining_time":0.2094499595},
{"learn":[3.344445461],"iteration":798,"passed_time":0.8282946974,"remaining_time":0.2083695046},
{"learn":[3.342608898],"iteration":799,"passed_time":0.8290544681,"remaining_time":0.207263617},
{"learn":[3.339572899],"iteration":800,"passed_time":0.8298510982,"remaining_time":0.206167751},
{"learn":[3.339309302],"iteration":801,"passed_time":0.8306098956,"remaining_time":0.2050632909},
{"learn":[3.33698088],"iteration":802,"passed_time":0.8313776404,"remaining_time":0.2039618869},
{"learn":[3.334746342],"iteration":803,"passed_time":0.832166704,"remaining_time":0.2028665099},
{"learn":[3.332048511],"iteration":804,"passed_time":0.8329775923,"remaining_time":0.2017771807},
{"learn":[3.331932544],"iteration":805,"passed_time":0.8336904341,"remaining_time":0.2006649432},
{"learn":[3.330541133],"iteration":806,"passed_time":0.8343761361,"remaining_time":0.1995472048},
{"learn":[3.329124989],"iteration":807,"passed_time":0.8350608734,"remaining_time":0.1984303065},
{"learn":[3.32583918],"iteration":808,"passed_time":0.8358254203,"remaining_time":0.1973333192},
{"learn":[3.325287299],"iteration":809,"passed_time":0.8365900596,"remaining_time":0.1962371745},
{"learn":[3.322745162],"iteration":810,"passed_time":0.8372787587,"remaining_time":0.1951241497},
{"learn":[3.319733662],"iteration":811,"passed_time":0.8395927021,"remaining_time":0.1943884581},
{"learn":[3.318080007],"iteration":812,"passed_time":0.8406129087,"remaining_time":0.1933513086},
{"learn":[3.317179538],"iteration":813,"passed_time":0.8414540313,"remaining_time":0.1922732799},
{"learn":[3.315685949],"iteration":814,"passed_time":0.8421983705,"remaining_time":0.1911738632},
{"learn":[3.314944576],"iteration":815,"passed_time":0.8429409699,"remaining_time":0.1900749246},
{"learn":[3.312369052],"iteration":816,"passed_time":0.8436768282,"remaining_time":0.1889753483},
{"learn":[3.312321621],"iteration":817,"passed_time":0.8442358833,"remaining_time":0.1878373237},
{"learn":[3.309465776],"iteration":818,"passed_time":0.8449742041,"remaining_time":0.1867403308},
{"learn":[3.308307377],"iteration":819,"passed_time":0.8456986457,"remaining_time":0.1856411661},
{"learn":[3.308076804],"iteration":820,"passed_time":0.8463979832,"remaining_time":0.1845374409},
{"learn":[3.305643326],"iteration":821,"passed_time":0.8471971178,"remaining_time":0.1834563102},
{"learn":[3.304154814],"iteration":822,"passed_time":0.8478557937,"remaining_time":0.1823456567},
{"learn":[3.303076321],"iteration":823,"passed_time":0.8485196424,"remaining_time":0.1812372052},
{"learn":[3.301746372],"iteration":824,"passed_time":0.8492913995,"remaining_time":0.1801527211},
{"learn":[3.301345455],"iteration":825,"passed_time":0.8499927709,"remaining_time":0.1790541672},
{"learn":[3.299181039],"iteration":826,"passed_time":0.8506940784,"remaining_time":0.1779565605},
{"learn":[3.297989357],"iteration":827,"passed_time":0.8513803284,"remaining_time":0.1768567832},
{"learn":[3.294775182],"iteration":828,"passed_time":0.8532027029,"remaining_time":0.1759923549},
{"learn":[3.293840636],"iteration":829,"passed_time":0.8545329402,"remaining_time":0.1750248191},
{"learn":[3.289279397],"iteration":830,"passed_time":0.8555192138,"remaining_time":0.1739864586},
{"learn":[3.286204979],"iteration":831,"passed_time":0.856528756,"remaining_time":0.1729529219},
{"learn":[3.284833593],"iteration":832,"passed_time":0.8572711454,"remaining_time":0.1718658839},
{"learn":[3.283519914],"iteration":833,"passed_time":0.8580103343,"remaining_time":0.1707790354},
{"learn":[3.282853026],"iteration":834,"passed_time":0.8587012337,"remaining_time":0.1696834773},
{"learn":[3.281944673],"iteration":835,"passed_time":0.8593870349,"remaining_time":0.1685878872},
{"learn":[3.279764865],"iteration":836,"passed_time":0.8600902712,"remaining_time":0.1674966717},
{"learn":[3.277468839],"iteration":837,"passed_time":0.8607642667,"remaining_time":0.1664007294},
{"learn":[3.277124974],"iteration":838,"passed_time":0.8614459187,"remaining_time":0.1653072621},
{"learn":[3.275636037],"iteration":839,"passed_time":0.8621402765,"remaining_time":0.1642171955},
{"learn":[3.274413635],"iteration":840,"passed_time":0.8627980497,"remaining_time":0.1631211533},
{"learn":[3.272636087],"iteration":841,"passed_time":0.8635597273,"remaining_time":0.1620456495},
{"learn":[3.269644466],"iteration":842,"passed_time":0.8643536974,"remaining_time":0.1609769045},
{"learn":[3.26852083],"iteration":843,"passed_time":0.8650959716,"remaining_time":0.1598992554},
{"learn":[3.267820927],"iteration":844,"passed_time":0.8658542606,"remaining_time":0.1588253377},
{"learn":[3.267331099],"iteration":845,"passed_time":0.8681790743,"remaining_time":0.1580373256},
{"learn":[3.267231014],"iteration":846,"passed_time":0.8692560128,"remaining_time":0.1570202715},
{"learn":[3.267158695],"iteration":847,"passed_time":0.8700126132,"remaining_time":0.1559456571},
{"learn":[3.264718705],"iteration":848,"passed_time":0.8706994365,"remaining_time":0.1548593815},
{"learn":[3.261678512],"iteration":849,"passed_time":0.871387812,"remaining_time":0.1537743198},
{"learn":[3.261368381],"iteration":850,"passed_time":0.8720521205,"remaining_time":0.1526859764},
{"learn":[3.260128799],"iteration":851,"passed_time":0.8727382192,"remaining_time":0.1516024137},
{"learn":[3.258972952],"iteration":852,"passed_time":0.8734435331,"remaining_time":0.1505230942},
{"learn":[3.258724846],"iteration":853,"passed_time":0.8741798931,"remaining_time":0.1494499583},
{"learn":[3.25686724],"iteration":854,"passed_time":0.8749356195,"remaining_time":0.1483808945},
{"learn":[3.255750259],"iteration":855,"passed_time":0.8756783711,"remaining_time":0.1473103802},
{"learn":[3.254915866],"iteration":856,"passed_time":0.8763720087,"remaining_time":0.1462324355},
{"learn":[3.254348625],"iteration":857,"passed_time":0.8770815509,"remaining_time":0.1451580189},
{"learn":[3.253408514],"iteration":858,"passed_time":0.8777720141,"remaining_time":0.1440813201},
{"learn":[3.253291714],"iteration":859,"passed_time":0.8784695345,"remaining_time":0.1430066684},
{"learn":[3.250186342],"iteration":860,"passed_time":0.8791964496,"remaining_time":0.1419376382},
{"learn":[3.249141318],"iteration":861,"passed_time":0.879933887,"remaining_time":0.1408710863},
{"learn":[3.246300388],"iteration":862,"passed_time":0.8806001832,"remaining_time":0.1397940036},
{"learn":[3.245205135],"iteration":863,"passed_time":0.8828591227,"remaining_time":0.1389685656},
{"learn":[3.244403535],"iteration":864,"passed_time":0.883814309,"remaining_time":0.1379363372},
{"learn":[3.244211781],"iteration":865,"passed_time":0.8846664262,"remaining_time":0.1368883385},
{"learn":[3.242286347],"iteration":866,"passed_time":0.8854799435,"remaining_time":0.1358348702},
{"learn":[3.239606746],"iteration":867,"passed_time":0.8862653074,"remaining_time":0.1347776735},
{"learn":[3.236773361],"iteration":868,"passed_time":0.8871131972,"remaining_time":0.133730528},
{"learn":[3.234552446],"iteration":869,"passed_time":0.8878044546,"remaining_time":0.1326604357},
{"learn":[3.233724647],"iteration":870,"passed_time":0.8885378025,"remaining_time":0.1315974472},
{"learn":[3.230851485],"iteration":871,"passed_time":0.8892624693,"remaining_time":0.1305339405},
{"learn":[3.227728941],"iteration":872,"passed_time":0.8899819061,"remaining_time":0.1294704491},
{"learn":[3.225787575],"iteration":873,"passed_time":0.890742708,"remaining_time":0.1284137085},
{"learn":[3.222797487],"iteration":874,"passed_time":0.8915772523,"remaining_time":0.1273681789},
{"learn":[3.22137014],"iteration":875,"passed_time":0.8923017721,"remaining_time":0.1263075568},
{"learn":[3.219701963],"iteration":876,"passed_time":0.8930220745,"remaining_time":0.1252471097},
{"learn":[3.21783327],"iteration":877,"passed_time":0.8937549878,"remaining_time":0.1241891897},
{"learn":[3.217713355],"iteration":878,"passed_time":0.8944508602,"remaining_time":0.1231269102},
{"learn":[3.217666091],"iteration":879,"passed_time":0.8954411973,"remaining_time":0.1221056178},
{"learn":[3.214962005],"iteration":880,"passed_time":0.8976301814,"remaining_time":0.1212463015},
{"learn":[3.214081828],"iteration":881,"passed_time":0.8984753179,"remaining_time":0.1202041808},
{"learn":[3.213358337],"iteration":882,"passed_time":0.8992811391,"remaining_time":0.119157297},
{"learn":[3.210850401],"iteration":883,"passed_time":0.9000491184,"remaining_time":0.1181059929},
{"learn":[3.207810328],"iteration":884,"passed_time":0.9008276142,"remaining_time":0.1170566956},
{"learn":[3.204935073],"iteration":885,"passed_time":0.9016471474,"remaining_time":0.1160132898},
{"learn":[3.20280198],"iteration":886,"passed_time":0.902436848,"remaining_time":0.1149665883},
{"learn":[3.200663495],"iteration":887,"passed_time":0.9032219665,"remaining_time":0.1139198877},
{"learn":[3.197301669],"iteration":888,"passed_time":0.904019906,"remaining_time":0.1128753763},
{"learn":[3.195666943],"iteration":889,"passed_time":0.9047689475,"remaining_time":0.1118253755},
{"learn":[3.193886506],"iteration":890,"passed_time":0.9055822412,"remaining_time":0.1107839105},
{"learn":[3.190601248],"iteration":891,"passed_time":0.9063537831,"remaining_time":0.109737902},
{"learn":[3.188983797],"iteration":892,"passed_time":0.9071013875,"remaining_time":0.1086896399},
{"learn":[3.187365749],"iteration":893,"passed_time":0.9079116379,"remaining_time":0.1076494783},
{"learn":[3.186160771],"iteration":894,"passed_time":0.9086321479,"remaining_time":0.1065993023},
{"learn":[3.185358981],"iteration":895,"passed_time":0.9111744819,"remaining_time":0.1057613238},
{"learn":[3.183832164],"iteration":896,"passed_time":0.9122526944,"remaining_time":0.1047514242},
{"learn":[3.183106966],"iteration":897,"passed_time":0.9130097202,"remaining_time":0.1037048903},
{"learn":[3.182838152],"iteration":898,"passed_time":0.9137738864,"remaining_time":0.1026598026},
{"learn":[3.180835453],"iteration":899,"passed_time":0.9144572251,"remaining_time":0.1016063583},
{"learn":[3.179957348],"iteration":900,"passed_time":0.9151678994,"remaining_time":0.1005567392},
{"learn":[3.179752966],"iteration":901,"passed_time":0.9158595703,"remaining_time":0.09950580697},
{"learn":[3.178851983],"iteration":902,"passed_time":0.9165965867,"remaining_time":0.09846054143},
{"learn":[3.176748586],"iteration":903,"passed_time":0.917339835,"remaining_time":0.09741661964},
{"learn":[3.172960988],"iteration":904,"passed_time":0.9182026242,"remaining_time":0.09638591083},
{"learn":[3.172794225],"iteration":905,"passed_time":0.9188819876,"remaining_time":0.09533654176},
{"learn":[3.169996507],"iteration":906,"passed_time":0.9197656948,"remaining_time":0.09430894114},
{"learn":[3.16813015],"iteration":907,"passed_time":0.9205040483,"remaining_time":0.09326693001},
{"learn":[3.166920871],"iteration":908,"passed_time":0.9212200359,"remaining_time":0.09222334793},
{"learn":[3.16531606],"iteration":909,"passed_time":0.9219638708,"remaining_time":0.09118323997},
{"learn":[3.162035247],"iteration":910,"passed_time":0.9226883452,"remaining_time":0.09014189103},
{"learn":[3.16189467],"iteration":911,"passed_time":0.9233797396,"remaining_time":0.08909804505},
{"learn":[3.161008416],"iteration":912,"passed_time":0.925571061,"remaining_time":0.08819789957},
{"learn":[3.160560787],"iteration":913,"passed_time":0.9265703867,"remaining_time":0.08718277162},
{"learn":[3.160416261],"iteration":914,"passed_time":0.9273885264,"remaining_time":0.08615084671},
{"learn":[3.15844291],"iteration":915,"passed_time":0.9281419676,"remaining_time":0.08511345555},
{"learn":[3.155040501],"iteration":916,"passed_time":0.9288474504,"remaining_time":0.08407234284},
{"learn":[3.154937548],"iteration":917,"passed_time":0.9295647407,"remaining_time":0.08303301605},
{"learn":[3.153721161],"iteration":918,"passed_time":0.9302334615,"remaining_time":0.08199010923},
{"learn":[3.153170511],"iteration":919,"passed_time":0.9309258015,"remaining_time":0.08095006969},
{"learn":[3.153113601],"iteration":920,"passed_time":0.931656006,"remaining_time":0.07991403309},
{"learn":[3.150607379],"iteration":921,"passed_time":0.9324755946,"remaining_time":0.07888622167},
{"learn":[3.148408359],"iteration":922,"passed_time":0.9332904045,"remaining_time":0.07785846278},
{"learn":[3.147495728],"iteration":923,"passed_time":0.9340617792,"remaining_time":0.07682759223},
{"learn":[3.146946235],"iteration":924,"passed_time":0.9347729258,"remaining_time":0.07579239939},
{"learn":[3.14472738],"iteration":925,"passed_time":0.9354866937,"remaining_time":0.07475811591},
{"learn":[3.144469477],"iteration":926,"passed_time":0.9362397542,"remaining_time":0.07372761819},
{"learn":[3.142975516],"iteration":927,"passed_time":0.9370186568,"remaining_time":0.07269972337},
{"learn":[3.14079113],"iteration":928,"passed_time":0.9376906545,"remaining_time":0.07166419426},
{"learn":[3.138173032],"iteration":929,"passed_time":0.9404931463,"remaining_time":0.07078980671},
{"learn":[3.136352813],"iteration":930,"passed_time":0.9414548301,"remaining_time":0.06977484777},
{"learn":[3.133735004],"iteration":931,"passed_time":0.9423227688,"remaining_time":0.06875316339},
{"learn":[3.1319496],"iteration":932,"passed_time":0.9430337103,"remaining_time":0.06772053439},
{"learn":[3.129865343],"iteration":933,"passed_time":0.9437907175,"remaining_time":0.06669184942},
{"learn":[3.129830206],"iteration":934,"passed_time":0.9443667732,"remaining_time":0.06565116605},
{"learn":[3.126676562],"iteration":935,"passed_time":0.9450936303,"remaining_time":0.06462178669},
{"learn":[3.12645665],"iteration":936,"passed_time":0.9458517873,"remaining_time":0.06359515752},
{"learn":[3.126378007],"iteration":937,"passed_time":0.9465469948,"remaining_time":0.06256493995},
{"learn":[3.124621914],"iteration":938,"passed_time":0.9472943621,"remaining_time":0.06153882438},
{"learn":[3.123379018],"iteration":939,"passed_time":0.9480438012,"remaining_time":0.06051343412},
{"learn":[3.123332451],"iteration":940,"passed_time":0.9487516801,"remaining_time":0.05948602458},
{"learn":[3.122432444],"iteration":941,"passed_time":0.9495371634,"remaining_time":0.05846407163},
{"learn":[3.121889006],"iteration":942,"passed_time":0.9502619908,"remaining_time":0.05743895384},
{"learn":[3.121070914],"iteration":943,"passed_time":0.9510386678,"remaining_time":0.05641754809},
{"learn":[3.118444705],"iteration":944,"passed_time":0.9518005236,"remaining_time":0.05539579767},
{"learn":[3.116820458],"iteration":945,"passed_time":0.9525454621,"remaining_time":0.05437363103},
{"learn":[3.114971041],"iteration":946,"passed_time":0.954659464,"remaining_time":0.05342867116},
{"learn":[3.114685138],"iteration":947,"passed_time":0.9558146934,"remaining_time":0.05242865407},
{"learn":[3.113399363],"iteration":948,"passed_time":0.9567648505,"remaining_time":0.05141728912},
{"learn":[3.110575399],"iteration":949,"passed_time":0.9574865531,"remaining_time":0.05039402911},
{"learn":[3.110466553],"iteration":950,"passed_time":0.9582774321,"remaining_time":0.04937496758},
{"learn":[3.108691641],"iteration":951,"passed_time":0.9589968327,"remaining_time":0.04835278148},
{"learn":[3.107898017],"iteration":952,"passed_time":0.9597577783,"remaining_time":0.04733327973},
{"learn":[3.105551729],"iteration":953,"passed_time":0.9604549348,"remaining_time":0.04631124423},
{"learn":[3.104824945],"iteration":954,"passed_time":0.9612220324,"remaining_time":0.04529318477},
{"learn":[3.103186704],"iteration":955,"passed_time":0.9619825427,"remaining_time":0.04427534715},
{"learn":[3.102330655],"iteration":956,"passed_time":0.9627855064,"remaining_time":0.04325995483},
{"learn":[3.102291298],"iteration":957,"passed_time":0.9634667045,"remaining_time":0.04223966763},
{"learn":[3.100363529],"iteration":958,"passed_time":0.964128948,"remaining_time":0.04121927724},
{"learn":[3.097871596],"iteration":959,"passed_time":0.9649477878,"remaining_time":0.04020615783},
{"learn":[3.097372213],"iteration":960,"passed_time":0.9656864683,"remaining_time":0.03919018966},
{"learn":[3.095981813],"iteration":961,"passed_time":0.9664590767,"remaining_time":0.03817613817},
{"learn":[3.095347452],"iteration":962,"passed_time":0.9684405116,"remaining_time":0.03720903316},
{"learn":[3.094728409],"iteration":963,"passed_time":0.9695265774,"remaining_time":0.03620638671},
{"learn":[3.094118537],"iteration":964,"passed_time":0.9703701111,"remaining_time":0.03519477087},
{"learn":[3.093793695],"iteration":965,"passed_time":0.9711290212,"remaining_time":0.03418052455},
{"learn":[3.092581602],"iteration":966,"passed_time":0.9718341686,"remaining_time":0.03316497163},
{"learn":[3.091694202],"iteration":967,"passed_time":0.972578354,"remaining_time":0.03215135055},
{"learn":[3.090298312],"iteration":968,"passed_time":0.9732887047,"remaining_time":0.03113720314},
{"learn":[3.090020107],"iteration":969,"passed_time":0.9740632975,"remaining_time":0.03012566899},
{"learn":[3.088949869],"iteration":970,"passed_time":0.974860184,"remaining_time":0.02911528871},
{"learn":[3.086700204],"iteration":971,"passed_time":0.9756018884,"remaining_time":0.0281037581},
{"learn":[3.086584317],"iteration":972,"passed_time":0.9762437199,"remaining_time":0.02709001073},
{"learn":[3.084850742],"iteration":973,"passed_time":0.9769668816,"remaining_time":0.02607919807},
{"learn":[3.084239948],"iteration":974,"passed_time":0.9777970388,"remaining_time":0.02507171894},
{"learn":[3.082561673],"iteration":975,"passed_time":0.9785751043,"remaining_time":0.02406332224},
{"learn":[3.07991814],"iteration":976,"passed_time":0.9793514351,"remaining_time":0.0230553562},
{"learn":[3.079350277],"iteration":977,"passed_time":0.9801336162,"remaining_time":0.02204799546},
{"learn":[3.077637462],"iteration":978,"passed_time":0.9809232076,"remaining_time":0.02104125369},
{"learn":[3.076733301],"iteration":979,"passed_time":0.9833308373,"remaining_time":0.02006797627},
{"learn":[3.07594065],"iteration":980,"passed_time":0.9842304642,"remaining_time":0.0190625676},
{"learn":[3.072594655],"iteration":981,"passed_time":0.9849876286,"remaining_time":0.01805476305},
{"learn":[3.071977674],"iteration":982,"passed_time":0.9856955798,"remaining_time":0.01704661735},
{"learn":[3.069532634],"iteration":983,"passed_time":0.9864536511,"remaining_time":0.01603989677},
{"learn":[3.068870784],"iteration":984,"passed_time":0.9873450878,"remaining_time":0.015035712},
{"learn":[3.068801463],"iteration":985,"passed_time":0.9881343825,"remaining_time":0.01403030563},
{"learn":[3.067433249],"iteration":986,"passed_time":0.9888916822,"remaining_time":0.01302491577},
{"learn":[3.065611456],"iteration":987,"passed_time":0.9896436846,"remaining_time":0.01201996378},
{"learn":[3.063039162],"iteration":988,"passed_time":0.9904196986,"remaining_time":0.01101579038},
{"learn":[3.06177873],"iteration":989,"passed_time":0.9912241802,"remaining_time":0.01001236546},
{"learn":[3.061689148],"iteration":990,"passed_time":0.9919409384,"remaining_time":0.009008545354},
{"learn":[3.058984039],"iteration":991,"passed_time":0.9926672517,"remaining_time":0.008005381062},
{"learn":[3.057492984],"iteration":992,"passed_time":0.9935278087,"remaining_time":0.007003720706},
{"learn":[3.057290731],"iteration":993,"passed_time":0.9943458442,"remaining_time":0.006002087591},
{"learn":[3.056068348],"iteration":994,"passed_time":0.9950552183,"remaining_time":0.005000277479},
{"learn":[3.054987307],"iteration":995,"passed_time":0.9970690499,"remaining_time":0.004004293373},
{"learn":[3.054200234],"iteration":996,"passed_time":0.9979977722,"remaining_time":0.003003002324},
{"learn":[3.052732869],"iteration":997,"passed_time":0.9989148501,"remaining_time":0.002001833367},
{"learn":[3.051787862],"iteration":998,"passed_time":0.9997536085,"remaining_time":0.001000754363},
{"learn":[3.051366222],"iteration":999,"passed_time":1.000493492,"remaining_time":0}
]}